[
  {
    "id": "1767755530143",
    "name": "Medicaid Telehealth Modal",
    "type": "html",
    "description": "Telehealth modal for the Health Choice Medicaid home page",
    "code": "<script>\n(function () {\n  /* ========================================\n     PREVENT DUPLICATE EXECUTION\n     ======================================== */\n  \n  if (window.modalScriptLoaded) {\n    console.log(\"Modal script already loaded, skipping duplicate execution\");\n    return;\n  }\n  window.modalScriptLoaded = true;\n\n  /* ========================================\n     CONFIG\n     ======================================== */\n  \n  var IFRAME_SRC;\n  var CHILD_ORIGIN;\n  \n  // Check if we're on staging\n  if (window.location.hostname === \"staging.azblue.com\") {\n    IFRAME_SRC = \"https://t-memberportal2.healthchoiceaz.com/Account/ExternalLogin\";\n    CHILD_ORIGIN = \"https://t-memberportal2.healthchoiceaz.com\";\n  } else {\n    // Production environment\n    IFRAME_SRC = \"https://memberportal.healthchoiceaz.com/Account/ExternalLogin\";\n    CHILD_ORIGIN = \"https://memberportal.healthchoiceaz.com\";\n  }\n\n  /* ========================================\n     LANGUAGE CHECK\n     ======================================== */\n  \n  var isSpanishPage = window.location.href.indexOf(\"/es/medicaid\") !== -1;\n  \n  if (isSpanishPage) {\n    IFRAME_SRC += (IFRAME_SRC.indexOf(\"?\") >= 0 ? \"&\" : \"?\") + \"lang=es\";\n  }\n\n  /* ========================================\n     SCROLL LOCK UTILITIES\n     ======================================== */\n  \n  var _scrollLock = {\n    y: 0,\n    prevBodyCss: \"\"\n  };\n\n  function lockScroll() {\n    _scrollLock.y = window.pageYOffset || 0;\n    _scrollLock.prevBodyCss = document.body.getAttribute(\"style\") || \"\";\n    \n    var scrollBarW = window.innerWidth - document.documentElement.clientWidth;\n    var padRight = scrollBarW > 0 ? \"padding-right:\" + scrollBarW + \"px;\" : \"\";\n    \n    document.body.setAttribute(\n      \"style\",\n      padRight + \n      \"position:fixed;\" +\n      \"top:-\" + _scrollLock.y + \"px;\" +\n      \"left:0;\" +\n      \"right:0;\" +\n      \"width:100%;\" +\n      \"overflow:hidden;\"\n    );\n    \n    document.addEventListener(\"touchmove\", preventBackgroundTouch, { passive: false });\n  }\n\n  function unlockScroll() {\n    if (_scrollLock.prevBodyCss) {\n      document.body.setAttribute(\"style\", _scrollLock.prevBodyCss);\n    } else {\n      document.body.removeAttribute(\"style\");\n    }\n    \n    window.scrollTo(0, _scrollLock.y || 0);\n    document.removeEventListener(\"touchmove\", preventBackgroundTouch, { passive: false });\n  }\n\n  function preventBackgroundTouch(e) {\n    var modal = document.getElementById(\"modalContent\");\n    if (!modal || !modal.contains(e.target)) {\n      e.preventDefault();\n    }\n  }\n\n  /* ========================================\n     CSS INJECTION (ANIMATION + RESPONSIVE)\n     ======================================== */\n  \n  function injectStyles() {\n    if (document.getElementById(\"dynamicModalStyles\")) return;\n    \n    var style = document.createElement(\"style\");\n    style.id = \"dynamicModalStyles\";\n    style.textContent =\n      \"#modalContent {\" +\n      \"  opacity: 0;\" +\n      \"  transform: scale(0.94);\" +\n      \"  transition: opacity .25s ease, transform .25s ease;\" +\n      \"}\" +\n      \"#modalContent.modal--visible {\" +\n      \"  opacity: 1;\" +\n      \"  transform: scale(1);\" +\n      \"}\" +\n      \"#modalContent {\" +\n      \"  width: 95vw;\" +\n      \"  max-width: 900px;\" +\n      \"}\" +\n      \"@media (min-width: 480px) {\" +\n      \"  #modalContent { width: 90vw; max-width: 600px; }\" +\n      \"}\" +\n      \"@media (min-width: 768px) {\" +\n      \"  #modalContent { width: 85vw; max-width: 750px; }\" +\n      \"}\" +\n      \"@media (min-width: 1024px) {\" +\n      \"  #modalContent { width: 95vw; max-width: 900px; }\" +\n      \"}\";\n    \n    document.head.appendChild(style);\n  }\n\n  /* ========================================\n     APPLY IFRAME HEIGHT (DYNAMIC)\n     ======================================== */\n  \n  function applyIframeHeight(iframe, height) {\n    var maxH = Math.floor(window.innerHeight * 0.9);\n    var clamped = Math.max(120, Math.min(height, maxH));\n    \n    console.log(\"DIAGNOSTIC — applyIframeHeight():\", height, \"-> clamped ->\", clamped);\n    iframe.style.height = clamped + \"px\";\n  }\n\n  /* ========================================\n     GLOBAL MESSAGE LOGGER\n     ======================================== */\n  \n  window.addEventListener(\"message\", function (e) {\n    console.log(\"DIAGNOSTIC — GLOBAL MESSAGE RECEIVED:\", e.data, \"from:\", e.origin);\n  });\n\n  /* ========================================\n     MODAL FACTORY\n     ======================================== */\n  \n  window.openModal = function () {\n    injectStyles();\n    \n    // Create modal overlay\n    var modal = document.createElement(\"div\");\n    modal.id = \"dynamicModal\";\n    modal.style.cssText =\n      \"position: fixed;\" +\n      \"inset: 0;\" +\n      \"background: rgba(0, 0, 0, 0.6);\" +\n      \"display: flex;\" +\n      \"align-items: center;\" +\n      \"justify-content: center;\" +\n      \"z-index: 9999;\";\n    \n    // Create modal content HTML\n    var contentHTML =\n      '<div id=\"modalContent\" style=\"' +\n        'background: #fff;' +\n        'padding: 20px;' +\n        'border-radius: 8px;' +\n        'overflow: hidden;' +\n        'max-height: 90vh;' +\n        'position: relative;' +\n        'box-shadow: 0 8px 24px rgba(0, 0, 0, .2);\">' +\n        '<button id=\"closeModal\" aria-label=\"Close\" title=\"Close\" style=\"' +\n          'position: absolute;' +\n          'top: 10px;' +\n          'right: 10px;' +\n          'background: none;' +\n          'border: none;' +\n          'font-size: 24px;' +\n          'cursor: pointer;' +\n          'line-height: 1\">×</button>' +\n        '<iframe id=\"dynamicIframe\" src=\"' + IFRAME_SRC + '\" frameborder=\"0\" style=\"' +\n          'display: block;' +\n          'width: 100%;' +\n          'height: 580px;' +\n          'border: none;' +\n          'transition: height .15s ease;\"></iframe>' +\n      '</div>';\n    \n    modal.innerHTML = contentHTML;\n    document.body.appendChild(modal);\n    lockScroll();\n    \n    var content = modal.querySelector(\"#modalContent\");\n    var iframe = modal.querySelector(\"#dynamicIframe\");\n    \n    // Trigger animation\n    setTimeout(function () {\n      content.classList.add(\"modal--visible\");\n    }, 20);\n\n    /* ========================================\n       DYNAMIC AUTOSIZING WITH DIAGNOSTICS\n       ======================================== */\n    \n    var fallbackTimer;\n    console.log(\"DIAGNOSTIC — Modal opened. Waiting for child height...\");\n\n    function onMessage(e) {\n      console.log(\"DIAGNOSTIC — onMessage() fired:\", e.data);\n      \n      // Validate origin\n      if (e.origin !== CHILD_ORIGIN) {\n        console.log(\"DIAGNOSTIC — IGNORED: origin mismatch:\", e.origin, \"!=\", CHILD_ORIGIN);\n        return;\n      }\n      \n      // Validate source\n      if (e.source !== iframe.contentWindow) {\n        console.log(\"DIAGNOSTIC — IGNORED: source mismatch\");\n        return;\n      }\n      \n      // Validate height\n      var newH = Number(e.data && e.data.iframeHeight);\n      if (!isFinite(newH) || newH <= 0) {\n        console.log(\"DIAGNOSTIC — IGNORED: invalid height:\", newH);\n        return;\n      }\n      \n      console.log(\"DIAGNOSTIC — VALID HEIGHT RECEIVED:\", newH);\n      \n      try {\n        clearTimeout(fallbackTimer);\n      } catch (err) {}\n      \n      applyIframeHeight(iframe, newH);\n    }\n\n    window.addEventListener(\"message\", onMessage);\n\n    // Handle iframe load\n    iframe.addEventListener(\"load\", function () {\n      console.log(\"DIAGNOSTIC — iframe load event. Sending handshake...\");\n      \n      try {\n        iframe.contentWindow.postMessage({ type: \"parent:init\" }, CHILD_ORIGIN);\n      } catch (err) {\n        console.log(\"DIAGNOSTIC — ERROR sending handshake:\", err);\n      }\n      \n      // Fallback to 580px if no reply\n      fallbackTimer = setTimeout(function () {\n        console.log(\"DIAGNOSTIC — Fallback fired: applying 580px\");\n        applyIframeHeight(iframe, 580);\n      }, 1800);\n    });\n\n    /* ========================================\n       CLEANUP & TEARDOWN\n       ======================================== */\n    \n    function teardown() {\n      console.log(\"DIAGNOSTIC — Modal closing. Cleaning up handlers...\");\n      \n      window.removeEventListener(\"message\", onMessage);\n      \n      try {\n        clearTimeout(fallbackTimer);\n      } catch (e) {}\n      \n      content.classList.remove(\"modal--visible\");\n      \n      setTimeout(function () {\n        if (modal && modal.parentNode) {\n          modal.parentNode.removeChild(modal);\n        }\n        unlockScroll();\n      }, 220);\n    }\n\n    // Close button handler\n    modal.querySelector(\"#closeModal\").onclick = teardown;\n    \n    // Click outside to close\n    modal.addEventListener(\"click\", function (evt) {\n      if (evt.target === modal) {\n        teardown();\n      }\n    });\n  };\n\n  /* ========================================\n     FIND AND WRAP \"POPULATION GROUPS\" TEXT\n     ======================================== */\n  \n  function wrapTextWithLink() {\n    var searchText = \"population groups\";\n    var walker = document.createTreeWalker(\n      document.body,\n      NodeFilter.SHOW_TEXT,\n      null,\n      false\n    );\n    \n    var node;\n    while (node = walker.nextNode()) {\n      var text = node.nodeValue;\n      var lowerText = text.toLowerCase();\n      var index = lowerText.indexOf(searchText);\n      \n      if (index !== -1) {\n        // Found the text, now wrap it in a link\n        var parent = node.parentNode;\n        \n        // Create the parts: before, link, after\n        var before = document.createTextNode(text.substring(0, index));\n        var linkText = text.substring(index, index + searchText.length);\n        var after = document.createTextNode(text.substring(index + searchText.length));\n        \n        // Create the link\n        var link = document.createElement(\"a\");\n        link.href = \"#\";\n        link.textContent = linkText;\n        link.onclick = function(e) {\n          e.preventDefault();\n          window.openModal();\n        };\n        \n        // Replace the text node with our new elements\n        parent.insertBefore(before, node);\n        parent.insertBefore(link, node);\n        parent.insertBefore(after, node);\n        parent.removeChild(node);\n        \n        console.log(\"Successfully wrapped 'population groups' with modal link\");\n        break; // Only wrap the first occurrence\n      }\n    }\n  }\n\n  /* ========================================\n     DUPLICATE MODAL BUTTON (STAGING ONLY)\n     ======================================== */\n  \n  var buttonDuplicatedFlag = false;\n  \n  function duplicateModalButton() {\n    // Only run on staging subdomain\n    if (window.location.hostname !== \"staging.azblue.com\") {\n      return;\n    }\n    \n    // Find all anchor tags\n    var links = document.querySelectorAll('a[href]');\n    \n    for (var i = 0; i < links.length; i++) {\n      var link = links[i];\n      var href = link.getAttribute('href');\n      \n      // Check if this is the target link\n      if (href === \"javascript:openModal()//;return false;\") {\n        // Check if we already added a duplicate next to this specific button\n        var nextSibling = link.nextSibling;\n        var alreadyDuplicated = false;\n        \n        if (nextSibling && nextSibling.nodeType === 1) {\n          var nextHref = nextSibling.getAttribute('href');\n          if (nextHref === 'javascript:openModal();' && \n              nextSibling.textContent === 'Dynamic Javascript Test Button') {\n            alreadyDuplicated = true;\n          }\n        }\n        \n        if (!alreadyDuplicated) {\n          console.log(\"Found target modal button, creating duplicate\");\n          \n          // Create duplicate link\n          var duplicate = link.cloneNode(true);\n          duplicate.setAttribute('href', 'javascript:openModal();');\n          \n          // Change button label\n          duplicate.textContent = 'Dynamic Javascript Test Button';\n          \n          // Apply absolute positioning and spacing\n          duplicate.style.position = 'absolute';\n          duplicate.style.marginLeft = '12px';\n          \n          // Insert duplicate after original\n          if (link.nextSibling) {\n            link.parentNode.insertBefore(duplicate, link.nextSibling);\n          } else {\n            link.parentNode.appendChild(duplicate);\n          }\n          \n          console.log(\"Successfully duplicated modal button\");\n        }\n        \n        break; // Only duplicate the first occurrence\n      }\n    }\n  }\n\n  // Set up MutationObserver for SPA navigation\n  function setupButtonObserver() {\n    if (window.location.hostname !== \"staging.azblue.com\") {\n      return;\n    }\n    \n    console.log(\"Setting up MutationObserver for SPA button duplication\");\n    \n    var observer = new MutationObserver(function(mutations) {\n      // Debounce: only run after mutations have settled\n      clearTimeout(window.buttonObserverTimeout);\n      window.buttonObserverTimeout = setTimeout(function() {\n        duplicateModalButton();\n      }, 100);\n    });\n    \n    observer.observe(document.body, {\n      childList: true,\n      subtree: true\n    });\n  }\n\n  // Run when DOM is ready\n  if (document.readyState === \"loading\") {\n    document.addEventListener(\"DOMContentLoaded\", function() {\n      wrapTextWithLink();\n      duplicateModalButton();\n      setupButtonObserver();\n    });\n  } else {\n    wrapTextWithLink();\n    duplicateModalButton();\n    setupButtonObserver();\n  }\n\n})();\n</script>",
    "demo": "",
    "date": "2026-01-07T03:12:10.143Z"
  },
  {
    "id": "1767363841541",
    "name": "Interactive Broker Calculator",
    "type": "html",
    "description": "Interactive tool for brokers",
    "code": "<!DOCTYPE html>\n<html lang=\"en\">\n<head>\n  <meta charset=\"UTF-8\" />\n  <meta name=\"viewport\" content=\"width=device-width, initial-scale=1.0\"/>\n  <title>ProSano Savings Calculator</title>\n  <style>\n    :root {\n      --bg-color: #f0f4fa;\n      --text-color: #000;\n      --panel-bg: #0c2f53;\n      --panel-text: #fff;\n      --slider-track: #cbd5e1;\n      --slider-fill: #f6c06f;\n      --thumb-color: #fff;\n      --cta-bg: #f6c06f;\n    }\n\n    body.dark {\n        --bg-color: #1e293b;\n    --text-color: #f8fafc;\n    --panel-bg: #e2e8f0;\n    --panel-text: #252525;\n    --slider-track: #64748b;\n    --slider-fill: #f6c06f;\n    --thumb-color: #fff;\n    --cta-bg: #f6c06f;\n    }\n\n    body {\n      background-color: #fff;\n      color: var(--text-color);\n      font-family: sans-serif;\n      margin: 0;\n      padding: 20px;\n    }\n\n    .wrapper {\n      max-width: 850px;\n      margin: auto;\n      background: var(--bg-color);\n      border-radius: 12px;\n      padding: 30px 60px 50px;\n      box-shadow: 0 0 4px rgba(0, 0, 0, 0.1);\n    }\n\n    .top-bar {\n      display: flex;\n      justify-content: space-between;\n      align-items: center;\n      margin-bottom: 30px;\n    }\n\n    .theme-toggle-container {\n      margin-top: 30px;\n      display: flex;\n      justify-content: center;\n    }\n\n    .toggle-switch {\n      position: relative;\n      width: 50px;\n      height: 26px;\n    }\n\n    .toggle-switch input {\n      opacity: 0;\n      width: 0;\n      height: 0;\n    }\n\n    .slider-toggle {\n      position: absolute;\n      cursor: pointer;\n      top: 0;\n      left: 0;\n      right: 0;\n      bottom: 0;\n      background-color: #ccc;\n      transition: 0.4s;\n      border-radius: 34px;\n    }\n\n    .slider-toggle:before {\n      position: absolute;\n      content: \"\";\n      height: 20px;\n      width: 20px;\n      left: 4px;\n      bottom: 3px;\n      background-color: white;\n      transition: 0.4s;\n      border-radius: 50%;\n    }\n\n    .toggle-switch input:checked + .slider-toggle {\n      background-color: var(--cta-bg);\n    }\n\n    .toggle-switch input:checked + .slider-toggle:before {\n      transform: translateX(24px);\n    }\n\n    .container {\n      display: flex;\n      gap: 40px;\n      flex-wrap: wrap;\n    }\n\n    .controls {\n      flex: 1;\n      min-width: 280px;\n    }\n\n    .control-group {\n      margin-bottom: 40px;\n    }\n\n    .group-size-pillset {\n      display: flex;\n      flex-wrap: nowrap;\n      overflow-x: auto;\n      gap: 12px;\n      margin-top: 16px;\n    }\n\n    .group-size-pillset label {\n      position: relative;\n      cursor: pointer;\n    }\n\n    .group-size-pillset input[type=\"radio\"] {\n      display: none;\n    }\n\n    .pill {\n  display: inline-flex;\n  align-items: center;\n  border: none;\n  border-radius: 9999px;\n  padding: 8px 16px;\n  font-size: 14px;\n  font-weight: 500;\n  color: var(--text-color);\n  background: #ffffff;\n  transition: all 0.2s ease;\n  white-space: nowrap;\n}\n\nbody.dark .pill {\n  background: #141c2a;\n}\n\n\n    .pill .check {\n      display: none;\n      margin-right: 8px;\n    }\n\n  .group-size-pillset input[type=\"radio\"]:checked + .pill {\n  border: none;\n  background-color: #0099D8;\n  color: #fff;\n  font-weight: bold;\n}\n\n    .group-size-pillset input[type=\"radio\"]:checked + .pill .check {\n      display: inline-block;\n    }\n\n    .slider-container {\n      position: relative;\n      padding-top: 48px;\n    }\n\n    .slider-labels {\n      display: flex;\n      justify-content: space-between;\n      font-size: 14px;\n      margin-top: 6px;\n      color: var(--text-color);\n      padding: 0 2px;\n    }\n\n    input[type=\"range\"] {\n      appearance: none;\n      width: 100%;\n      height: 8px;\n      margin-top: 15px;\n      background: transparent;\n    }\n\n    input[type=\"range\"]::-webkit-slider-runnable-track {\n  height: 8px;\n  background: none;\n  border-radius: 4px;\n}\n\n    input[type=\"range\"]::-webkit-slider-thumb {\n      appearance: none;\n      width: 20px;\n      height: 20px;\n      background: var(--thumb-color);\n      border: 3px solid var(--slider-fill);\n      border-radius: 50%;\n      cursor: pointer;\n      margin-top: -6px;\n      position: relative;\n      z-index: 2;\n    }\n\n    .value-display {\n        position: absolute;\n    top: 25px;\n    right: 0;\n    background: #fff;\n    color: #000;\n    padding: 10px 18px;\n    font-size: 18px;\n    font-weight: bold;\n    border-radius: 4px;\n    /* border: 1px solid #ccc; */\n    /* box-shadow: 0 2px 4px rgba(0, 0, 0, 0.2); */\n    white-space: nowrap;\n    pointer-events: none;\n    z-index: 3;\n\n    }\n\n    .estimate-panel {\n      background: var(--panel-bg);\n      color: var(--panel-text);\n      border-radius: 12px;\n      padding: 30px;\n      flex: 0 0 280px;\n      min-width: 260px;\n    }\n\n    .estimate-panel h2 {\n      font-size: 20px;\n      margin-bottom: 10px;\n    }\n\n    .savings {\n      font-size: 36px;\n      font-weight: bold;\n      margin: 10px 0;\n    }\n\n    .cta {\n      background-color: var(--cta-bg);\n      border: none;\n      padding: 12px 20px;\n      font-size: 16px;\n      border-radius: 4px;\n      cursor: pointer;\n      margin-top: 20px;\n      width: 100%;\n    }\n\n    @media (max-width: 768px) {\n      .container {\n        flex-direction: column;\n      }\n      .estimate-panel, .controls {\n        width: 100%;\n      }\n    }\n  </style>\n</head>\n<body>\n\n<div class=\"wrapper\">\n  <div class=\"top-bar\">\n    <h1 style=\"margin: 20px auto;\">See how much you can save with Prosano Health</h1>\n  </div>\n\n  <div class=\"container\">\n    <div class=\"controls\">\n      <div style=\"margin-top:40px\" class=\"control-group\">\n        <label style=\"font-weight:bold;font-size: 14px;\" for=\"groupSize\">Group Size</label>\n        <div class=\"group-size-pillset\">\n          <label><input type=\"radio\" name=\"groupSize\" value=\"under10\" checked><span class=\"pill\"><span class=\"check\">&#10003;</span>Under 10</span></label>\n          <label><input type=\"radio\" name=\"groupSize\" value=\"10to50\"><span class=\"pill\"><span class=\"check\">&#10003;</span>10–50</span></label>\n          <label><input type=\"radio\" name=\"groupSize\" value=\"50to100\"><span class=\"pill\"><span class=\"check\">&#10003;</span>50–100</span></label>\n          <label><input type=\"radio\" name=\"groupSize\" value=\"100to300\"><span class=\"pill\"><span class=\"check\">&#10003;</span>100–300</span></label>\n          <label><input type=\"radio\" name=\"groupSize\" value=\"300plus\"><span class=\"pill\"><span class=\"check\">&#10003;</span>300+</span></label>\n        </div>\n       \n      </div>\n\n      <div style=\"margin-top:40px;\" class=\"control-group\">\n        \n        <div class=\"slider-container\">\n            <label style=\"font-weight:bold;font-size: 14px;\" for=\"utilization\">Percent of employees getting care at Prosano Health</label>\n          <input type=\"range\" id=\"utilization\" min=\"10\" max=\"100\" step=\"1\" value=\"50\">\n          <div class=\"value-display\" id=\"utilizationDisplay\">50%</div>\n          <div class=\"slider-labels\">\n            <span>10%</span>\n            <span>100%</span>\n          </div>\n        </div>\n       \n      </div>\n    </div>\n\n    <div class=\"estimate-panel\">\n      <h2 style=\"font-size:18px;\">Estimated Savings</h2>\n      <div class=\"savings\" id=\"savingsAmount\">$3,250</div>\n      <p style=\"font-size: 12px;\">Estimated Annual Savings</p>\n      <h3 style=\"font-size: 24px; margin-bottom:0;margin-top:50px\">Save Big with Prosano</h3>\n      <p style=\"font-size: 14px;line-height: 22px;\">Lorem ipsum dolor sit amet, ius ei dicat altera. Error moderatius eu mei. Te etiam putant sed.</p>\n      <button class=\"cta\">Shop Plans</button>\n    </div>\n  </div>\n</div>\n\n<div class=\"theme-toggle-container\">\n  <label class=\"toggle-switch\">\n    <input type=\"checkbox\" id=\"toggleMode\" />\n    <span class=\"slider-toggle\"></span>\n  </label>\n</div>\n\n<script>\n  const utilizationSlider = document.getElementById('utilization');\n  const utilizationDisplay = document.getElementById('utilizationDisplay');\n  const savingsAmount = document.getElementById('savingsAmount');\n  const toggleMode = document.getElementById('toggleMode');\n\n  function getGroupEstimate(category, utilization) {\n    const u = utilization / 100;\n    switch (category) {\n      case \"under10\": return Math.round(130 * 10 * u);\n      case \"10to50\": return Math.round(130 * 50 * u);\n      case \"50to100\": return Math.round(150000 * u);\n      case \"100to300\": return Math.round(300000 * u);\n      case \"300plus\": return Math.round(650000 * u);\n      default: return 0;\n    }\n  }\n\n  function updateDisplay() {\n    const value = parseInt(utilizationSlider.value, 10);\n    utilizationDisplay.textContent = value + '%';\n\n    const groupValue = document.querySelector('input[name=\"groupSize\"]:checked').value;\n    const estimated = getGroupEstimate(groupValue, value);\n    savingsAmount.textContent = '$' + estimated.toLocaleString();\n\n    const min = parseInt(utilizationSlider.min, 10);\n    const max = parseInt(utilizationSlider.max, 10);\n    const percent = (value - min) / (max - min);\n\n    const fillPercent = percent * 100;\n    utilizationSlider.style.background = `linear-gradient(to right, var(--slider-fill) 0%, var(--slider-fill) ${fillPercent}%, var(--slider-track) ${fillPercent}%, var(--slider-track) 100%)`;\n  }\n\n  utilizationSlider.addEventListener('input', updateDisplay);\n  document.querySelectorAll('input[name=\"groupSize\"]').forEach(input =>\n    input.addEventListener('change', updateDisplay)\n  );\n\n  toggleMode.addEventListener('change', () => {\n    document.body.classList.toggle('dark');\n  });\n\n  window.addEventListener('load', updateDisplay);\n</script>\n\n</body>\n</html>",
    "demo": "",
    "date": "2026-01-02T14:24:01.542Z"
  },
  {
    "id": "1767274916631",
    "name": "SVG Inspector",
    "type": "html",
    "description": "Inspect SVG inline code",
    "code": "<!DOCTYPE html>\n<html lang=\"en\">\n<head>\n    <meta charset=\"UTF-8\">\n    <meta name=\"viewport\" content=\"width=device-width, initial-scale=1.0\">\n    <title>SVG Viewer</title>\n    <style>\n        * {\n            margin: 0;\n            padding: 0;\n            box-sizing: border-box;\n        }\n\n        body {\n            font-family: -apple-system, BlinkMacSystemFont, 'Segoe UI', 'Helvetica Neue', Arial, sans-serif;\n            padding: 48px 24px;\n            background: #ffffff;\n            min-height: 100vh;\n            color: #1a1a1a;\n        }\n\n        .container {\n            max-width: 800px;\n            margin: 0 auto;\n        }\n\n        h1 {\n            margin-bottom: 32px;\n            color: #1a1a1a;\n            font-size: 28px;\n            font-weight: 400;\n            letter-spacing: -0.02em;\n        }\n\n        .preview-box {\n            position: relative;\n            width: 100%;\n            min-height: 400px;\n            border: 1px solid #e0e0e0;\n            margin-bottom: 24px;\n            background: #fafafa;\n            padding: 20px;\n            display: none;\n        }\n\n        .preview-box.active {\n            display: block;\n        }\n\n        .button-container {\n            position: absolute;\n            top: 16px;\n            right: 16px;\n            display: flex;\n            gap: 8px;\n            z-index: 10;\n        }\n\n        .icon-button {\n            width: 36px;\n            height: 36px;\n            border: 1px solid #e0e0e0;\n            background: #ffffff;\n            cursor: pointer;\n            display: flex;\n            align-items: center;\n            justify-content: center;\n            transition: background-color 0.2s;\n            color: #1a1a1a;\n        }\n\n        .icon-button:hover {\n            background: #f5f5f5;\n        }\n\n        .icon-button:active {\n            background: #ebebeb;\n        }\n\n        .icon-button svg {\n            width: 18px;\n            height: 18px;\n            stroke: #1a1a1a;\n        }\n\n        .copy-button {\n            display: none;\n        }\n\n        .copy-button.active {\n            display: flex;\n        }\n\n        .zoom-controls {\n            display: none;\n        }\n\n        .zoom-controls.active {\n            display: flex;\n            gap: 8px;\n        }\n\n        .copy-feedback {\n            position: absolute;\n            top: 50%;\n            left: 50%;\n            transform: translate(-50%, -50%);\n            background: #1a1a1a;\n            color: #ffffff;\n            padding: 10px 20px;\n            font-size: 14px;\n            pointer-events: none;\n            opacity: 0;\n            transition: opacity 0.3s;\n        }\n\n        .copy-feedback.show {\n            opacity: 1;\n        }\n\n        .svg-display {\n            width: 100%;\n            height: 100%;\n            display: flex;\n            align-items: center;\n            justify-content: center;\n            min-height: 360px;\n            overflow: hidden;\n            position: relative;\n            cursor: grab;\n        }\n\n        .svg-display.grabbing {\n            cursor: grabbing;\n        }\n\n        .svg-container {\n            transition: transform 0.1s ease-out;\n            transform-origin: center center;\n        }\n\n        .svg-container svg {\n            max-width: 100%;\n            max-height: 360px;\n        }\n\n        .code-display {\n            display: none;\n            width: 100%;\n            height: 360px;\n            overflow: auto;\n            background: #fafafa;\n            color: #1a1a1a;\n            padding: 0;\n            font-family: 'SF Mono', 'Monaco', 'Courier New', monospace;\n            font-size: 13px;\n            line-height: 1.6;\n            white-space: pre;\n            border: 1px solid #e0e0e0;\n        }\n\n        .code-content {\n            padding: 60px 20px 20px 20px;\n        }\n\n        .code-display.active {\n            display: block;\n        }\n\n        .code-display::-webkit-scrollbar {\n            width: 8px;\n            height: 8px;\n        }\n\n        .code-display::-webkit-scrollbar-track {\n            background: transparent;\n        }\n\n        .code-display::-webkit-scrollbar-thumb {\n            background: #d0d0d0;\n        }\n\n        .code-display::-webkit-scrollbar-thumb:hover {\n            background: #b0b0b0;\n        }\n\n        .file-input-container {\n            margin-top: 24px;\n            position: relative;\n        }\n\n        .file-input-wrapper {\n            position: relative;\n            display: block;\n        }\n\n        input[type=\"file\"] {\n            padding: 16px 60px 16px 20px;\n            border: 1px solid #e0e0e0;\n            background: #ffffff;\n            color: #1a1a1a;\n            cursor: pointer;\n            font-size: 14px;\n            transition: background-color 0.2s;\n            width: 100%;\n            font-family: -apple-system, BlinkMacSystemFont, 'Segoe UI', 'Helvetica Neue', Arial, sans-serif;\n        }\n\n        input[type=\"file\"]:hover {\n            background: #fafafa;\n        }\n\n        input[type=\"file\"]::file-selector-button {\n            display: none;\n        }\n\n        .file-icon-button {\n            position: absolute;\n            right: 12px;\n            top: 50%;\n            transform: translateY(-50%);\n            width: 32px;\n            height: 32px;\n            border: none;\n            background: transparent;\n            cursor: pointer;\n            display: flex;\n            align-items: center;\n            justify-content: center;\n            pointer-events: none;\n        }\n\n        .file-icon-button svg {\n            width: 20px;\n            height: 20px;\n            stroke: #1a1a1a;\n        }\n\n        .error-message {\n            color: #d32f2f;\n            margin-top: 12px;\n            font-size: 14px;\n            display: none;\n            padding: 12px 16px;\n            background: #fef2f2;\n            border-left: 2px solid #d32f2f;\n        }\n\n        .error-message.active {\n            display: block;\n        }\n    </style>\n</head>\n<body>\n    <div class=\"container\">\n        <h1>SVG Viewer</h1>\n        \n        <div class=\"preview-box\" id=\"previewBox\">\n            <div class=\"button-container\">\n                <div class=\"zoom-controls\" id=\"zoomControls\">\n                    <button class=\"icon-button\" id=\"zoomOutBtn\" title=\"Zoom Out\">\n                        <svg viewBox=\"0 0 24 24\" fill=\"none\" stroke=\"currentColor\" stroke-width=\"2\" stroke-linecap=\"round\" stroke-linejoin=\"round\">\n                            <circle cx=\"11\" cy=\"11\" r=\"8\"></circle>\n                            <line x1=\"21\" y1=\"21\" x2=\"16.65\" y2=\"16.65\"></line>\n                            <line x1=\"8\" y1=\"11\" x2=\"14\" y2=\"11\"></line>\n                        </svg>\n                    </button>\n                    <button class=\"icon-button\" id=\"zoomResetBtn\" title=\"Reset Zoom\">\n                        <svg viewBox=\"0 0 24 24\" fill=\"none\" stroke=\"currentColor\" stroke-width=\"2\" stroke-linecap=\"round\" stroke-linejoin=\"round\">\n                            <path d=\"M3 12a9 9 0 0 1 9-9 9.75 9.75 0 0 1 6.74 2.74L21 8\"></path>\n                            <path d=\"M21 3v5h-5\"></path>\n                            <path d=\"M21 12a9 9 0 0 1-9 9 9.75 9.75 0 0 1-6.74-2.74L3 16\"></path>\n                            <path d=\"M3 21v-5h5\"></path>\n                        </svg>\n                    </button>\n                    <button class=\"icon-button\" id=\"zoomInBtn\" title=\"Zoom In\">\n                        <svg viewBox=\"0 0 24 24\" fill=\"none\" stroke=\"currentColor\" stroke-width=\"2\" stroke-linecap=\"round\" stroke-linejoin=\"round\">\n                            <circle cx=\"11\" cy=\"11\" r=\"8\"></circle>\n                            <line x1=\"21\" y1=\"21\" x2=\"16.65\" y2=\"16.65\"></line>\n                            <line x1=\"11\" y1=\"8\" x2=\"11\" y2=\"14\"></line>\n                            <line x1=\"8\" y1=\"11\" x2=\"14\" y2=\"11\"></line>\n                        </svg>\n                    </button>\n                </div>\n                <button class=\"icon-button copy-button\" id=\"copyBtn\" title=\"Copy SVG Code\">\n                    <svg viewBox=\"0 0 24 24\" fill=\"none\" stroke=\"currentColor\" stroke-width=\"2\" stroke-linecap=\"round\" stroke-linejoin=\"round\">\n                        <rect x=\"9\" y=\"9\" width=\"13\" height=\"13\" rx=\"2\" ry=\"2\"></rect>\n                        <path d=\"M5 15H4a2 2 0 0 1-2-2V4a2 2 0 0 1 2-2h9a2 2 0 0 1 2 2v1\"></path>\n                    </svg>\n                </button>\n                <button class=\"icon-button\" id=\"inspectBtn\" title=\"Inspect SVG Code\">\n                    <svg viewBox=\"0 0 24 24\" fill=\"none\" stroke=\"currentColor\" stroke-width=\"2\">\n                        <polyline points=\"16 18 22 12 16 6\"></polyline>\n                        <polyline points=\"8 6 2 12 8 18\"></polyline>\n                    </svg>\n                </button>\n                <button class=\"icon-button\" id=\"clearBtn\" title=\"Clear\">\n                    <svg viewBox=\"0 0 24 24\" fill=\"none\" stroke=\"currentColor\" stroke-width=\"2\">\n                        <line x1=\"18\" y1=\"6\" x2=\"6\" y2=\"18\"></line>\n                        <line x1=\"6\" y1=\"6\" x2=\"18\" y2=\"18\"></line>\n                    </svg>\n                </button>\n            </div>\n            \n            <div class=\"copy-feedback\" id=\"copyFeedback\">Copied!</div>\n            \n            <div class=\"svg-display\" id=\"svgDisplay\"></div>\n            <div class=\"code-display\" id=\"codeDisplay\">\n                <div class=\"code-content\" id=\"codeContent\"></div>\n            </div>\n        </div>\n\n        <div class=\"file-input-container\">\n            <div class=\"file-input-wrapper\">\n                <input type=\"file\" id=\"svgFileInput\" accept=\".svg,image/svg+xml\">\n                <div class=\"file-icon-button\">\n                    <svg viewBox=\"0 0 24 24\" fill=\"none\" stroke=\"currentColor\" stroke-width=\"2\" stroke-linecap=\"round\" stroke-linejoin=\"round\">\n                        <path d=\"M22 19a2 2 0 0 1-2 2H4a2 2 0 0 1-2-2V5a2 2 0 0 1 2-2h5l2 3h9a2 2 0 0 1 2 2z\"></path>\n                    </svg>\n                </div>\n            </div>\n            <div class=\"error-message\" id=\"errorMessage\"></div>\n        </div>\n    </div>\n\n    <script>\n        const fileInput = document.getElementById('svgFileInput');\n        const previewBox = document.getElementById('previewBox');\n        const svgDisplay = document.getElementById('svgDisplay');\n        const codeDisplay = document.getElementById('codeDisplay');\n        const codeContent = document.getElementById('codeContent');\n        const inspectBtn = document.getElementById('inspectBtn');\n        const clearBtn = document.getElementById('clearBtn');\n        const copyBtn = document.getElementById('copyBtn');\n        const copyFeedback = document.getElementById('copyFeedback');\n        const errorMessage = document.getElementById('errorMessage');\n        const zoomControls = document.getElementById('zoomControls');\n        const zoomInBtn = document.getElementById('zoomInBtn');\n        const zoomOutBtn = document.getElementById('zoomOutBtn');\n        const zoomResetBtn = document.getElementById('zoomResetBtn');\n\n        let svgContent = '';\n        let isCodeView = false;\n        let scale = 1;\n        let translateX = 0;\n        let translateY = 0;\n        let isDragging = false;\n        let startX = 0;\n        let startY = 0;\n        let svgContainer = null;\n\n        fileInput.addEventListener('change', function(e) {\n            const file = e.target.files[0];\n            \n            if (!file) return;\n\n            if (!file.type.match('image/svg.*') && !file.name.endsWith('.svg')) {\n                showError('Please select a valid SVG file.');\n                return;\n            }\n\n            const reader = new FileReader();\n            \n            reader.onload = function(event) {\n                svgContent = event.target.result;\n                displaySVG(svgContent);\n                hideError();\n                previewBox.classList.add('active');\n                isCodeView = false;\n                zoomControls.classList.add('active');\n                updateInspectButton();\n            };\n\n            reader.onerror = function() {\n                showError('Error reading file. Please try again.');\n            };\n\n            reader.readAsText(file);\n        });\n\n        function displaySVG(content) {\n            const wrapper = document.createElement('div');\n            wrapper.className = 'svg-container';\n            wrapper.innerHTML = content;\n            svgDisplay.innerHTML = '';\n            svgDisplay.appendChild(wrapper);\n            svgContainer = wrapper;\n            \n            codeContent.textContent = formatXML(content);\n            svgDisplay.style.display = 'flex';\n            codeDisplay.classList.remove('active');\n            \n            resetZoom();\n        }\n\n        function formatXML(xml) {\n            let formatted = '';\n            let indent = '';\n            const tab = '  ';\n            \n            xml.split(/>\\s*</).forEach(function(node) {\n                if (node.match(/^\\/\\w/)) indent = indent.substring(tab.length);\n                formatted += indent + '<' + node + '>\\n';\n                if (node.match(/^<?\\w[^>]*[^\\/]$/)) indent += tab;\n            });\n            \n            return formatted.substring(1, formatted.length - 2);\n        }\n\n        inspectBtn.addEventListener('click', function() {\n            isCodeView = !isCodeView;\n            \n            if (isCodeView) {\n                svgDisplay.style.display = 'none';\n                codeDisplay.classList.add('active');\n                copyBtn.classList.add('active');\n                zoomControls.classList.remove('active');\n            } else {\n                svgDisplay.style.display = 'flex';\n                codeDisplay.classList.remove('active');\n                copyBtn.classList.remove('active');\n                zoomControls.classList.add('active');\n            }\n            \n            updateInspectButton();\n        });\n\n        function updateInspectButton() {\n            if (isCodeView) {\n                inspectBtn.innerHTML = `\n                    <svg viewBox=\"0 0 24 24\" fill=\"none\" stroke=\"currentColor\" stroke-width=\"2\">\n                        <rect x=\"3\" y=\"3\" width=\"18\" height=\"18\" rx=\"2\" ry=\"2\"></rect>\n                        <circle cx=\"8.5\" cy=\"8.5\" r=\"1.5\"></circle>\n                        <polyline points=\"21 15 16 10 5 21\"></polyline>\n                    </svg>\n                `;\n                inspectBtn.title = 'View Image';\n            } else {\n                inspectBtn.innerHTML = `\n                    <svg viewBox=\"0 0 24 24\" fill=\"none\" stroke=\"currentColor\" stroke-width=\"2\">\n                        <polyline points=\"16 18 22 12 16 6\"></polyline>\n                        <polyline points=\"8 6 2 12 8 18\"></polyline>\n                    </svg>\n                `;\n                inspectBtn.title = 'Inspect SVG Code';\n            }\n        }\n\n        copyBtn.addEventListener('click', function() {\n            navigator.clipboard.writeText(svgContent).then(function() {\n                copyFeedback.classList.add('show');\n                setTimeout(function() {\n                    copyFeedback.classList.remove('show');\n                }, 2000);\n            }).catch(function(err) {\n                console.error('Failed to copy: ', err);\n            });\n        });\n\n        function updateTransform() {\n            if (svgContainer) {\n                svgContainer.style.transform = `translate(${translateX}px, ${translateY}px) scale(${scale})`;\n            }\n        }\n\n        function resetZoom() {\n            scale = 1;\n            translateX = 0;\n            translateY = 0;\n            updateTransform();\n        }\n\n        zoomInBtn.addEventListener('click', function() {\n            scale = Math.min(scale * 1.2, 5);\n            updateTransform();\n        });\n\n        zoomOutBtn.addEventListener('click', function() {\n            scale = Math.max(scale / 1.2, 0.1);\n            translateX = 0;\n            translateY = 0;\n            updateTransform();\n        });\n\n        zoomResetBtn.addEventListener('click', function() {\n            resetZoom();\n        });\n\n        svgDisplay.addEventListener('wheel', function(e) {\n            if (!isCodeView && svgContainer) {\n                e.preventDefault();\n                const delta = e.deltaY > 0 ? 0.9 : 1.1;\n                scale = Math.min(Math.max(scale * delta, 0.1), 5);\n                updateTransform();\n            }\n        });\n\n        svgDisplay.addEventListener('mousedown', function(e) {\n            if (!isCodeView && svgContainer) {\n                isDragging = true;\n                startX = e.clientX - translateX;\n                startY = e.clientY - translateY;\n                svgDisplay.classList.add('grabbing');\n            }\n        });\n\n        document.addEventListener('mousemove', function(e) {\n            if (isDragging) {\n                translateX = e.clientX - startX;\n                translateY = e.clientY - startY;\n                updateTransform();\n            }\n        });\n\n        document.addEventListener('mouseup', function() {\n            isDragging = false;\n            svgDisplay.classList.remove('grabbing');\n        });\n\n        clearBtn.addEventListener('click', function() {\n            fileInput.value = '';\n            svgDisplay.innerHTML = '';\n            codeContent.textContent = '';\n            svgContent = '';\n            svgContainer = null;\n            previewBox.classList.remove('active');\n            isCodeView = false;\n            copyBtn.classList.remove('active');\n            zoomControls.classList.remove('active');\n            resetZoom();\n            hideError();\n            updateInspectButton();\n        });\n\n        function showError(message) {\n            errorMessage.textContent = message;\n            errorMessage.classList.add('active');\n        }\n\n        function hideError() {\n            errorMessage.classList.remove('active');\n        }\n    </script>\n</body>\n</html>",
    "demo": "",
    "date": "2026-01-01T13:41:56.632Z"
  },
  {
    "id": "1767274340037",
    "name": "Letter Grid",
    "type": "html",
    "description": "Abstraction generator based on letter forms",
    "code": "<!DOCTYPE html>\n<html lang=\"en\">\n<head>\n    <meta charset=\"UTF-8\">\n    <meta name=\"viewport\" content=\"width=device-width, initial-scale=1.0\">\n    <title>Downloadable Rotating Characters Grid</title>\n    <style>\n        @import url('https://use.typekit.net/sdx3aek.css');\n    </style>\n    <script src=\"https://cdnjs.cloudflare.com/ajax/libs/jquery/3.3.1/jquery.min.js\"></script>\n    <script src=\"https://cdnjs.cloudflare.com/ajax/libs/FileSaver.js/2.0.0/FileSaver.min.js\"></script>\n\n    <style>\n        body {\n            display: flex;\n            flex-direction: row;\n            justify-content: center;\n            align-items: center;\n            padding: 0;\n            margin: 0;\n            height: 100vh;\n            overflow: hidden;\n            background-color: #fff;\n        }\n        .controls {\n            display: flex;\n            flex-direction: column;\n            justify-content: center;\n            align-items: flex-start;\n            padding: 30px;\n            background-color: #fff;\n            position: fixed;\n            left: 0;\n            width: 300px; /* Adjust this value based on the width of your controls */\n            box-shadow: 2px 2px 2px 0px #ddd;\n            z-index: 999;\n            transition: left 0.3s ease;\n            top: unset;\n            bottom: unset;\n        }\n        .controls:hover {\n            left: 0 !important;\n        }\n        .controls::before {\n            content: '❯';\n            position: absolute;\n            top: 50%;\n            right: -30px; /* Width of the visible edge */\n            width: 30px;\n            height: 30px;\n            background-color: #fff;\n            display: flex;\n            align-items: center;\n            justify-content: center;\n            transform: translateY(-50%);\n            font-size: 20px;\n            color: #666;\n            cursor: pointer;\n        }\n        .buttons {\n            display: flex;\n            justify-content: space-between;\n            width: 100%;\n        }\n        .button {\n            width: 48%;\n            height: 50px;\n            font-size: 16px;\n            padding: 0 10px;\n            margin: 10px 0;\n            border: 1px solid #ddd;\n            background-color: #f3f3f3;\n            color: #666;\n            cursor: pointer;\n            text-align: center;\n        }\n        .grid {\n            display: grid;\n    grid-template-columns: repeat(3, 1fr);\n    grid-template-rows: repeat(3, 1fr);\n    width: 80vmin;\n    height: 80vmin;\n    max-width: 800px;\n    max-height: 800px;\n    background-color: #fff;\n    border: 40px solid #fff;\n    border-radius: 5px;\n        }\n        .cell {\n            display: flex;\n    justify-content: center;\n    align-items: center;\n    overflow: hidden;\n    background-color: #fff;\n    border: 1px solid #fff;\n    border-radius: 5px;\n        }\n        .letter {\n            display: inline-block;\n            transform-origin:left center;\n            color: #FFD495;\n            position: relative;\n            opacity: 0;\n            text-align: center;\n            transition: all 0.3s ease-out;\n        }\n        @keyframes fadeIn {\n            from {\n                opacity: 0;\n            }\n            to {\n                opacity: 1;\n            }\n        }\n        select {\n            width: 100%;\n            height: 50px;\n            font-size: 18px;\n            padding: 0 10px;\n            margin: 10px 0px 20px 0px;\n            border: 1px solid #ddd;\n            color: #666;\n        }\n        label {\n            font-size: 18px;\n            font-family: system-ui;\n        }\n    </style>\n</head>\n<body>\n    <div class=\"controls\">\n        <label for=\"fontSelector\">Select Font Family:</label>\n        <select id=\"fontSelector\">\n            <option value=\"default\" disabled selected>Select an option</option>\n            <option value=\"brother-1816\">Brother 1816</option>\n            <option value=\"yink\">Yink</option>\n            <option value=\"selfie-neue-round\">Selfie Neue Round</option>\n            <option value=\"rafaella\">Rafaella</option>\n            <option value=\"fabiola-script\">Fabiola Script</option>\n            <option value=\"komet\">Komet</option>\n            <option value=\"fit\">Fit</option>\n            <option value=\"roc-grotesk\">Roc Grotesk</option>\n        </select>\n        <label for=\"fontSizeSelector\">Select Font Size (based on width of grid cell):</label>\n        <select id=\"fontSizeSelector\">\n            <option value=\"default\" disabled selected>Select an option</option>\n            <option value=\".3\">View Characters</option>\n            <option value=\"2\">x2</option>\n            <option value=\"3\">x3</option>\n            <option value=\"4\">x4</option>\n            <option value=\"5\">x5</option>\n            <option value=\"6\">x6</option>\n            <option value=\"7\">x7</option>\n            <option value=\"8\">x8</option>\n            <option value=\"9\">x9</option>\n            <option value=\"10\">x10</option>\n        </select>\n        <div style=\"margin-bottom: 20px; display: flex; align-items: center; width: 100%;\">\n            <label for=\"fontStyleCheckbox\" style=\"margin-right: 10px;\">Italic:</label>\n            <input type=\"checkbox\" id=\"fontStyleCheckbox\" style=\"margin-right: 20px;\">\n            <label for=\"fontWeightSelector\" style=\"margin-right: 10px;\">Weight:</label>\n            <select id=\"fontWeightSelector\" style=\"flex-grow: 1; width: 100%;\">\n                <option value=\"400\">400</option>\n                <option value=\"500\">500</option>\n                <option value=\"600\">600</option>\n                <option value=\"700\">700</option>\n                <option value=\"800\">800</option>\n                <option value=\"900\">900</option>\n            </select>\n        </div>\n        <div class=\"buttons\">\n            <button class=\"button refresh-button\" onclick=\"location.reload();\">Refresh Grid</button>\n            <button class=\"button\" id=\"clearLocalStorage\">Clear Settings</button>\n        </div>\n    </div>\n    <div id=\"alphabetGrid\" class=\"grid\"></div>\n    <!-- <button id=\"download\">Download</button> -->\n\n    <script>\n         const characters = \"abcdefghijklmnopqrstuvwxyz&ABCDEFGHIJKLMNOPQRSTUVWXYZ\".split('');\n        //const characters = \"abcdegmnopqrs?&\".split('');\n        const colors = [\"#FD665C\", \"#FD665C\", \"#FD665C\", \"#FD665C\", \"#FD665C\", \"#FD665C\", \"#FD665C\", \"#FD665C\", \"#F8E2CF\", \"#AAD1D9\", \"#FAF7F5\"];\n        //const colors =  ['#ccc5b9', '#252422', '#403d39', '#eb5e28', '#fffcf2'];\n       // const colors =  ['#ccc5b9', '#252422', '#403d39', '#eb5e28', '#fffcf2', 'eb5e28', 'eb5e28', 'eb5e28', 'eb5e28'];\n        let fontSizeMultiplier = .3;\n\n        function getRandomFromArray(arr) {\n            return arr[Math.floor(Math.random() * arr.length)];\n        }\n\n        function createAlphabetGrid(rows, columns) {\n            let grid = [];\n            for (let i = 0; i < rows; i++) {\n                for (let j = 0; j < columns; j++) {\n                    let cell = document.createElement('div');\n                    cell.className = 'cell';\n                    let letterContainer = document.createElement('span');\n                    letterContainer.className = 'letter';\n                    let character = getRandomFromArray(characters);\n                    let color = getRandomFromArray(colors);\n\n                    letterContainer.textContent = character;\n                    letterContainer.style.color = color;\n\n                    cell.appendChild(letterContainer);\n                    grid.push(cell);\n                }\n            }\n            return grid;\n        }\n\n        function setFontSizes() {\n            const cells = document.querySelectorAll('.cell');\n            cells.forEach(cell => {\n                const letterContainer = cell.querySelector('.letter');\n                const cellWidth = cell.offsetWidth;\n                const fontSize = cellWidth * fontSizeMultiplier;\n                letterContainer.style.fontSize = `${fontSize}px`;\n            });\n        }\n\n        function applySettings() {\n            const savedFont = localStorage.getItem('selectedFont');\n            const savedFontStyle = localStorage.getItem('selectedFontStyle');\n            const savedFontWeight = localStorage.getItem('selectedFontWeight');\n            if (savedFont) {\n                changeFontFamily(savedFont);\n            }\n            if (savedFontStyle === 'italic') {\n                document.getElementById('fontStyleCheckbox').checked = true;\n                changeFontStyle('italic');\n            }\n            if (savedFontWeight) {\n                document.getElementById('fontWeightSelector').value = savedFontWeight;\n                changeFontWeight(savedFontWeight);\n            }\n            const letters = document.querySelectorAll('.letter');\n            letters.forEach((letter, index) => {\n                setTimeout(() => {\n                    letter.style.opacity = 1;\n                    letter.style.animation = \"fadeIn 0.5s ease-out\";\n                }, index * 100);\n            });\n        }\n\n        function loadSettings() {\n            const savedFont = localStorage.getItem('selectedFont');\n            const savedFontSize = localStorage.getItem('selectedFontSize');\n            const savedFontStyle = localStorage.getItem('selectedFontStyle');\n            const savedFontWeight = localStorage.getItem('selectedFontWeight');\n\n            console.log('Saved font:', savedFont);  // Debugging log\n            console.log('Saved font size:', savedFontSize);  // Debugging log\n            console.log('Saved font style:', savedFontStyle);  // Debugging log\n            console.log('Saved font weight:', savedFontWeight);  // Debugging log\n\n            if (savedFont) {\n                document.getElementById('fontSelector').value = savedFont;\n            }\n            if (savedFontSize) {\n                document.getElementById('fontSizeSelector').value = savedFontSize;\n                fontSizeMultiplier = parseFloat(savedFontSize);\n            }\n            if (savedFontStyle === 'italic') {\n                document.getElementById('fontStyleCheckbox').checked = true;\n            }\n            if (savedFontWeight) {\n                document.getElementById('fontWeightSelector').value = savedFontWeight;\n            }\n        }\n\n        function saveSettings() {\n            const selectedFont = document.getElementById('fontSelector').value;\n            const selectedFontSize = document.getElementById('fontSizeSelector').value;\n            const selectedFontStyle = document.getElementById('fontStyleCheckbox').checked ? 'italic' : 'normal';\n            const selectedFontWeight = document.getElementById('fontWeightSelector').value;\n\n            console.log('Saving font:', selectedFont);  // Debugging log\n            console.log('Saving font size:', selectedFontSize);  // Debugging log\n            console.log('Saving font style:', selectedFontStyle);  // Debugging log\n            console.log('Saving font weight:', selectedFontWeight);  // Debugging log\n\n            localStorage.setItem('selectedFont', selectedFont);\n            localStorage.setItem('selectedFontSize', selectedFontSize);\n            localStorage.setItem('selectedFontStyle', selectedFontStyle);\n            localStorage.setItem('selectedFontWeight', selectedFontWeight);\n        }\n\n        function clearSettings() {\n            localStorage.removeItem('selectedFont');\n            localStorage.removeItem('selectedFontSize');\n            localStorage.removeItem('selectedFontStyle');\n            localStorage.removeItem('selectedFontWeight');\n            location.reload();\n        }\n\n        function changeFontFamily(fontFamily) {\n            console.log('Changing font family to:', fontFamily);  // Debugging log\n            const letters = document.querySelectorAll('.letter');\n            letters.forEach(letter => {\n                letter.style.fontFamily = fontFamily;\n                console.log('Applied font family to letter:', letter.textContent);  // Debugging log\n            });\n            setFontSizes();\n        }\n\n        function changeFontStyle(fontStyle) {\n            console.log('Changing font style to:', fontStyle);  // Debugging log\n            const letters = document.querySelectorAll('.letter');\n            letters.forEach(letter => {\n                letter.style.fontStyle = fontStyle;\n                console.log('Applied font style to letter:', letter.textContent);  // Debugging log\n            });\n        }\n\n        function changeFontWeight(fontWeight) {\n            console.log('Changing font weight to:', fontWeight);  // Debugging log\n            const letters = document.querySelectorAll('.letter');\n            letters.forEach(letter => {\n                letter.style.fontWeight = fontWeight;\n                console.log('Applied font weight to letter:', letter.textContent);  // Debugging log\n            });\n        }\n\n        document.getElementById('fontSelector').addEventListener('change', function() {\n            const selectedFont = this.value;\n            changeFontFamily(selectedFont);\n            saveSettings();\n        });\n\n        document.getElementById('fontSizeSelector').addEventListener('change', function() {\n            fontSizeMultiplier = parseFloat(this.value);\n            setFontSizes();\n            saveSettings();\n        });\n\n        document.getElementById('fontStyleCheckbox').addEventListener('change', function() {\n            const fontStyle = this.checked ? 'italic' : 'normal';\n            changeFontStyle(fontStyle);\n            saveSettings();\n        });\n\n        document.getElementById('fontWeightSelector').addEventListener('change', function() {\n            const fontWeight = this.value;\n            changeFontWeight(fontWeight);\n            saveSettings();\n        });\n\n        document.getElementById('clearLocalStorage').addEventListener('click', clearSettings);\n\n        loadSettings();  // Ensure settings are loaded before creating the grid\n\n        const rows = 3;\n        const columns = 3;\n        const grid = createAlphabetGrid(rows, columns);\n        displayGrid(grid);  // Define and call displayGrid after loading settings\n\n        function displayGrid(grid) {\n            const gridContainer = document.getElementById('alphabetGrid');\n            grid.forEach((cell, index) => {\n                setTimeout(() => {\n                    cell.style.opacity = 1;\n                    cell.style.animation = \"fadeIn 0.5s ease-out\";\n                    gridContainer.appendChild(cell);\n                    if (index === grid.length - 1) {\n                        setTimeout(() => {\n                            setFontSizes();\n                            applySettings();  // Apply settings after the grid is displayed\n                        }, 0);\n                    }\n                }, index * 100);\n            });\n        }\n\n        // Check if the mouse is over the controls when the page loads\n        let mouseIsOverControls = false;\n\n        document.querySelector('.controls').addEventListener('mouseover', function() {\n            mouseIsOverControls = true;\n            this.style.left = '0';\n        });\n\n        document.querySelector('.controls').addEventListener('mouseout', function() {\n            mouseIsOverControls = false;\n            this.style.left = '-350px';\n        });\n\n        // Slide the controls out after page load if the mouse is not over the controls\n        window.addEventListener('load', function() {\n            setTimeout(() => {\n                if (!mouseIsOverControls) {\n                    document.querySelector('.controls').style.left = '-350px';\n                }\n            }, 300);  // Adjust the timeout as needed\n        });\n    </script>\n</body>\n</html>\n",
    "demo": "",
    "date": "2026-01-01T13:32:20.038Z"
  },
  {
    "id": "1767256546363",
    "name": "Animated Form Thank You Page",
    "type": "html",
    "description": "Simple and clean thank you page for form submissions",
    "code": "<!DOCTYPE html>\n<html lang=\"en\"><head>\n<meta charset=\"utf-8\"/>\n<meta content=\"width=device-width, initial-scale=1.0\" name=\"viewport\"/>\n<title>Thank You</title>\n<link href=\"https://fonts.googleapis.com\" rel=\"preconnect\"/>\n<link crossorigin=\"\" href=\"https://fonts.gstatic.com\" rel=\"preconnect\"/>\n<link href=\"https://fonts.googleapis.com/css2?family=Inter:wght@400;500;600;700&amp;display=swap\" rel=\"stylesheet\"/>\n<link href=\"https://fonts.googleapis.com/css2?family=Material+Symbols+Outlined\" rel=\"stylesheet\"/>\n<script src=\"https://cdn.tailwindcss.com?plugins=forms,container-queries\"></script>\n<script>\n      tailwind.config = {\n        darkMode: \"class\",\n        theme: {\n          extend: {\n            colors: {\n              primary: \"#137fec\",\n              \"background-light\": \"#f6f7f8\",\n              \"background-dark\": \"#101922\",\n              \"button-bg\": \"#FFBE5F\",\n              \"button-label\": \"#0b3b60\",\n            },\n            fontFamily: {\n              display: [\"Inter\"],\n            },\n            borderRadius: {\n              DEFAULT: \"0.25rem\",\n              lg: \"0.5rem\",\n              xl: \"0.75rem\",\n              full: \"9999px\",\n            },\n          },\n        },\n      };\n</script>\n<style>\n      .material-symbols-outlined {\n        font-variation-settings:\n          \"FILL\" 1,\n          \"wght\" 400,\n          \"GRAD\" 0,\n          \"opsz\" 24;\n      }\n      \n      /* Animation styles only */\n      .thank-you-container {\n        opacity: 0;\n        transform: translateY(30px);\n        transition: all 0.6s cubic-bezier(0.4, 0, 0.2, 1);\n      }\n\n      .thank-you-container.show {\n        opacity: 1;\n        transform: translateY(0);\n      }\n\n      .thank-you-header {\n        opacity: 0;\n        transform: translateY(20px);\n        transition: all 0.6s cubic-bezier(0.4, 0, 0.2, 1) 0.2s;\n      }\n\n      .thank-you-container.show .thank-you-header {\n        opacity: 1;\n        transform: translateY(0);\n      }\n\n      .card {\n        opacity: 0;\n        transform: translateY(20px);\n        transition: all 0.6s cubic-bezier(0.4, 0, 0.2, 1);\n      }\n\n      .card:first-child {\n        transition-delay: 0.4s;\n      }\n\n      .card:last-child {\n        transition-delay: 0.6s;\n      }\n\n      .thank-you-container.show .card {\n        opacity: 1;\n        transform: translateY(0);\n      }\n</style>\n</head>\n<body class=\"font-display bg-background-light dark:bg-background-dark\">\n<div class=\"flex h-screen items-center justify-center p-4\">\n<div class=\"w-full max-w-4xl rounded-xl border border-white/10 bg-white dark:bg-background-dark/50 shadow-lg thank-you-container\" id=\"thankYouContainer\">\n<div class=\"flex flex-col items-center p-8 text-center sm:p-12 thank-you-header\">\n<h1 class=\"text-2xl font-bold text-slate-800 dark:text-slate-100 sm:text-3xl mt-8\">\n            Thank you for your submission!\n          </h1>\n<p class=\"mt-2 max-w-2xl text-base text-slate-600 dark:text-slate-400\">\n            We appreciate you taking the time to share your thoughts. Your\n            feedback is valuable and helps us improve our services for everyone.\n          </p>\n</div>\n<div class=\"grid grid-cols-1 gap-px border-t border-slate-200 bg-slate-200 dark:border-slate-700 dark:bg-slate-700 md:grid-cols-2\">\n<div class=\"flex flex-col items-start bg-background-light p-8 text-left dark:bg-background-dark card\">\n<h3 class=\"text-lg font-semibold text-slate-800 dark:text-slate-100\">\n              Explore Our Resources\n            </h3>\n<p class=\"mt-2 text-sm text-slate-600 dark:text-slate-400\">\n              Dive deeper into what we offer. Check out our latest articles,\n              guides, and case studies to learn more.\n            </p>\n<a class=\"mt-6 flex items-center justify-center rounded-full bg-button-bg px-5 py-2.5 text-sm font-semibold text-button-label transition-all hover:bg-opacity-90 focus-visible:outline focus-visible:outline-2 focus-visible:outline-offset-2 focus-visible:outline-button-bg\" href=\"#\">Explore More</a>\n</div>\n<div class=\"flex flex-col items-start bg-background-light p-8 text-left dark:bg-background-dark card\">\n<h3 class=\"text-lg font-semibold text-slate-800 dark:text-slate-100\">\n              Have More Questions?\n            </h3>\n<p class=\"mt-2 text-sm text-slate-600 dark:text-slate-400\">\n              Our support team is here to help. If you have any further\n              questions, don't hesitate to get in touch.\n            </p>\n<a class=\"mt-6 flex items-center justify-center rounded-full bg-button-bg/20 px-5 py-2.5 text-sm font-semibold text-button-label transition-colors hover:bg-button-bg/30 focus-visible:outline focus-visible:outline-2 focus-visible:outline-offset-2 focus-visible:outline-button-bg\" href=\"#\">Contact Us</a>\n</div>\n</div>\n</div>\n</div>\n\n<script>\nwindow.addEventListener('load', function() {\n    const thankYouContainer = document.getElementById('thankYouContainer');\n    setTimeout(() => {\n        thankYouContainer.classList.add('show');\n    }, 100);\n});\n</script>\n</body></html>",
    "demo": "",
    "date": "2026-01-01T08:35:46.364Z"
  },
  {
    "id": "1767255554821",
    "name": "Wallpaper Generator",
    "type": "html",
    "description": "Generates Responsive Bauhaus Style Wallpaper",
    "code": "<!DOCTYPE html>\n<html lang=\"en\">\n<head>\n  <meta charset=\"UTF-8\">\n  <meta name=\"viewport\" content=\"width=device-width, initial-scale=1.0\">\n  <title>Bauhaus Grid</title>\n  <style>\n    body, html {\n      margin: 0;\n      padding: 0;\n      overflow-x: hidden;\n    }\n\n    canvas {\n      display: block;\n      width: 100vw;\n      background: #f0f0f0;\n    }\n\n    #downloadBtn, #refreshBtn, #randomPaletteBtn, #christmasBtn {\n      max-width: 200px;\n      box-shadow: 1px 1px 1px #0000003b;\n      opacity: 1;\n      color: #333;\n      font-weight: 400;\n      text-transform: uppercase;\n      font-size: 13px;\n       font-family: \"Noto Sans\", sans-serif;\n      display: inline-flex;\n      align-items: center;\n    }\n\n    #downloadBtn:hover, #refreshBtn:hover, #randomPaletteBtn:hover, #christmasBtn:hover {\n      opacity: 1;\n    }\n\n    .buttons {\n      position: absolute;\n      left: 2%;\n      bottom: 0px;\n      height: 60px;\n    }\n\n    button {\n       font-family: \"Noto Sans\", sans-serif;\n    background-color: #fff;\n    display: inline-block;\n    padding: 8px 20px 8px 16px;\n    /* margin-right: 5px; */\n    cursor: pointer;\n    margin: 0px;\n    border: 1px solid aliceblue;\n    border-right-color: #cdcdcd;\n    margin-left: -4px;\n    }\n    #downloadBtn:hover, #refreshBtn:hover, #randomPaletteBtn:hover, #christmasBtn:hover{\n     background-color: aliceblue;\n    }\n\n    .fa {\n      margin-right: 8px;\n    }\n  </style>\n  <!-- Font Awesome CDN -->\n  <link rel=\"stylesheet\" href=\"https://cdnjs.cloudflare.com/ajax/libs/font-awesome/6.0.0-beta3/css/all.min.css\">\n  <link rel=\"preconnect\" href=\"https://fonts.googleapis.com\">\n<link rel=\"preconnect\" href=\"https://fonts.gstatic.com\" crossorigin>\n<link href=\"https://fonts.googleapis.com/css2?family=Noto+Sans:ital,wght@0,100..900;1,100..900&display=swap\" rel=\"stylesheet\">\n</head>\n\n<body>\n  <div class=\"buttons\">\n    <button id=\"downloadBtn\"><i class=\"fa fa-download\"></i>Download</button>\n    <button onclick=\"refreshPage()\" id=\"refreshBtn\"><i class=\"fa fa-sync-alt\"></i>AZ Blue</button>\n    <button onclick=\"christmasMode()\" id=\"christmasBtn\"><i class=\"fa fa-tree\"></i>AZ Blue Christmas</button>\n    <button onclick=\"randomPalette()\" id=\"randomPaletteBtn\"><i class=\"fa fa-palette\"></i>Random</button>\n  </div>\n  <canvas id=\"gridCanvas\" width=\"1440\" height=\"960\"></canvas>\n\n  <script>\n    const canvas = document.getElementById('gridCanvas');\n    const ctx = canvas.getContext('2d');\n\n    let minCellsAcross = 8;\n    let isChristmasMode = true;\n    let selectedSvgDesign = 3; // Always use design 3 (snowflakes with varied sizes)\n    // Commented out random selection - uncomment to enable multiple SVG designs:\n    // let selectedSvgDesign = Math.floor(Math.random() * 4);\n\n    // Christmas color palette for SVG\n    const christmasColors = ['#FBB24C', '#E7EAF1', '#F58220', '#0099D8', '#FFFFFF', '#F1F9FD'];\n\n    const colorPalettes = [\n      ['#F58220', '#FBB24C', '#0099D8', '#FFFFFF', '#E7EAF1'], // AZ Blue\n      ['#F1AA00', '#F525BC', '#ED2992', '#C11DB3', '#45A5F2', '#94EAA4', '#ffffff'], // Pow!\n      ['#FEC028', '#EE5A31', '#1F2A39', '#F8A4BC', '#7B9AAB', '#A89E32', '#0B806B', '#ffffff'], // Tropics\n      ['#444343', '#2d2c2c', '#312f2f', '#3b3a3a', '#1a1a1a'], //Carbon\n      ['#ccc5b9', '#252422', '#403d39', '#eb5e28', '#fffcf2'], //Terracotta\n      ['#026173', '#fa8a57', '#dda850', '#e9bg9c', '#db5659', '#b5d5ca'], //Terra\n      ['#D23031', '#F54337', '#B71B1C', '#FF9C00', '#FF6100'], // Ember\n      ['#9E50BE', '#D680D9', '#300EA1', '#6D28C3', '#F2C2F4'], // Orchid\n      ['#4E8098', '#A2C3DB', '#E7D4C9', '#FB9F89', '#EF6F6C'], // Dream\n      ['#0F4C81', '#2A7B9B', '#F18F01', '#F06000', '#D9C8B4'], // Punch\n      ['#88CCF1', '#F76C5E', '#F9A620', '#2A2E32', '#E4E4E4'], //Tucan\n      ['#1A535C', '#4ECDC4', '#FF6B6B', '#FFE66D', '#F7FFF7'], // Exotica\n      ['#03060D', '#011C26', '#014040', '#185941', '#F2F2F2'], // Swampthing\n      ['#001542', '#085454', '#7A7A7A', '#FFFFFF', '#FFB30D'], // Swampthing\n      ['#0597F2', '#05AFF2', '#05C7F2', '#F2D479', '#D96523'], // Swampthing\n      ['#025159', '#038C5A', '#04D976', '#03A65A', '#04D960'], // Swampthing\n      ['#593C23', '#BFAE9F', '#A65C41', '#401B13', '#8C2920'], // Swampthing\n      ['#3D5A73', '#2F3D40', '#455559', '#28403D', '#182625'], // Swampthing\n      ['#8A74B2', '#BB738A', '#E87264', '#F98162', '#FFAE82'], // Swampthing\n    ];\n\n    let colors = colorPalettes[0]; // Start with AZ Blue palette (Christmas mode)\n\n    function setCanvasSize() {\n      canvas.width = window.innerWidth;\n      const cellSize = canvas.width / minCellsAcross;\n      const rows = Math.ceil(window.innerHeight / cellSize);\n      canvas.height = rows * cellSize;\n    }\n\n    function calculateGrid() {\n      const cellSize = canvas.width / minCellsAcross;\n      const cols = Math.floor(canvas.width / cellSize);\n      const rows = Math.floor(canvas.height / cellSize);\n      return { cellSize, rows, cols };\n    }\n\n    function drawGrid() {\n      ctx.clearRect(0, 0, canvas.width, canvas.height);\n      const { cellSize, rows, cols } = calculateGrid();\n\n      for (let row = 0; row < rows; row++) {\n        for (let col = 0; col < cols; col++) {\n          ctx.fillStyle = 'transparent';\n          ctx.strokeStyle = 'transparent';\n\n          const bgColor = colors[Math.floor(Math.random() * colors.length)];\n          ctx.fillStyle = getFillStyle(bgColor, col * cellSize, row * cellSize, cellSize);\n          ctx.fillRect(col * cellSize, row * cellSize, cellSize, cellSize);\n\n          const shapeColors = colors.filter(c => c !== bgColor);\n          const shapeColor = shapeColors[Math.floor(Math.random() * shapeColors.length)];\n\n          if (isChristmasMode) {\n            drawSvgShape(ctx, col * cellSize, row * cellSize, cellSize, bgColor);\n          } else {\n            drawQuarterCircle(ctx, col * cellSize, row * cellSize, cellSize, shapeColor);\n          }\n        }\n      }\n    }\n\n    function getFillStyle(color, x, y, size) {\n      return color;\n    }\n\n    function drawQuarterCircle(context, x, y, size, color) {\n      context.fillStyle = color;\n      const corners = ['top-left', 'top-right', 'bottom-left', 'bottom-right'];\n      const corner = corners[Math.floor(Math.random() * corners.length)];\n\n      context.beginPath();\n      switch (corner) {\n        case 'top-left':\n          context.moveTo(x, y);\n          context.arc(x, y, size, 0, Math.PI / 2);\n          break;\n        case 'top-right':\n          context.moveTo(x + size, y);\n          context.arc(x + size, y, size, Math.PI / 2, Math.PI);\n          break;\n        case 'bottom-left':\n          context.moveTo(x, y + size);\n          context.arc(x, y + size, size, 1.5 * Math.PI, 0);\n          break;\n        case 'bottom-right':\n          context.moveTo(x + size, y + size);\n          context.arc(x + size, y + size, size, Math.PI, 1.5 * Math.PI);\n          break;\n      }\n      context.closePath();\n      context.fill();\n    }\n\n    function getRandomColors() {\n      // Shuffle the colors array and pick first 3\n      const availableColors = [...christmasColors];\n      const shuffled = availableColors.sort(() => Math.random() - 0.5);\n      return {\n        cls2: shuffled[0],\n        cls3: shuffled[1],\n        cls4: shuffled[2]\n      };\n    }\n\n    function drawSvgShape(context, x, y, size, bgColor) {\n      // Get three random colors different from background and from each other\n      const colorSet = getRandomColors();\n      // Random rotation: 0, 90, 180, or 270 degrees\n      const rotations = [0, 90, 180, 270];\n      const rotation = rotations[Math.floor(Math.random() * rotations.length)];\n      \n      // New snowflake design with stars\n      // Three light background options\n      const bgOptions = ['#FFFFFF', '#E7EAF1', '#F1F9FD'];\n      \n      // Filter out the quarter circle color if it matches any background option\n      const availableBgs = bgOptions.filter(bg => bg !== colorSet.cls2);\n      \n      // If quarter circle isn't a light color, use all options; otherwise use filtered list\n      const lightBg = availableBgs.length === bgOptions.length \n        ? bgOptions[Math.floor(Math.random() * bgOptions.length)]\n        : availableBgs[Math.floor(Math.random() * availableBgs.length)];\n      \n      const svgString = `<?xml version=\"1.0\" encoding=\"UTF-8\"?>\n<svg id=\"Layer_1\" xmlns=\"http://www.w3.org/2000/svg\" viewBox=\"82.66 1.24 80 80\">\n  <defs>\n    <style>.cls-1,.cls-2,.cls-3{fill:none;}.cls-4{fill:${colorSet.cls2};}.cls-5{fill:${colorSet.cls3};}.cls-2{stroke-width:.5px;}.cls-2,.cls-3{stroke:${colorSet.cls4};stroke-linecap:round;stroke-linejoin:round;}.cls-3{stroke-width:.25px;}.cls-6{fill:${colorSet.cls4};}.cls-8{clip-path:url(#clippath);}.cls-9{fill:${colorSet.cls2};}</style>\n    <clipPath id=\"clippath\"><rect class=\"cls-1\" x=\"82.66\" y=\"1.24\" width=\"80\" height=\"80\"/></clipPath>\n  </defs>\n  <g class=\"cls-8\" transform=\"rotate(${rotation} 122.66 41.24)\">\n    <rect fill=\"${lightBg}\" x=\"82.66\" y=\"1.24\" width=\"80\" height=\"80\"/>\n    <path class=\"cls-4\" d=\"M82.66,1.24h0v80h80C162.66,37.05,126.85,1.24,82.66,1.24Z\"/>\n    <path class=\"cls-6\" d=\"M97.79,44.52h-4.62l3.27-3.27c.13-.13.13-.35,0-.48-.13-.13-.35-.13-.48,0l-3.27,3.27v-4.62c0-.19-.15-.34-.34-.34s-.34.15-.34.34v4.62l-3.27-3.27c-.13-.13-.35-.13-.48,0-.13.13-.13.35,0,.48l3.27,3.27h-4.62c-.19,0-.34.15-.34.34s.15.34.34.34h4.62l-3.27,3.27c-.13.13-.13.35,0,.48.07.07.15.1.24.1s.17-.03.24-.1l3.27-3.27v4.62c0,.19.15.34.34.34s.34-.15.34-.34v-4.62l3.27,3.27c.07.07.15.1.24.1s.17-.03.24-.1c.13-.13.13-.35,0-.48l-3.27-3.27h4.62c.19,0,.34-.15.34-.34s-.15-.34-.34-.34Z\"/>\n    <path class=\"cls-6\" d=\"M91.88,64.89c.12.12.57,1.44.66,1.69.51.22,1.09.43,1.62.62-.5.19-1.12.42-1.61.63-.13.31-.56,1.68-.68,1.83-.21-.54-.41-1.32-.65-1.83-.55-.2-1.1-.4-1.64-.63.55-.2,1.10-.42,1.64-.63.23-.54.42-1.14.66-1.69Z\"/>\n    <path class=\"cls-5\" d=\"M55.67,37.01h-12.62l8.92-8.92c.36-.36.36-.94,0-1.31s-.94-.36-1.31,0l-8.92,8.92v-12.62c0-.51-.41-.92-.92-.92s-.92.41-.92.92v12.62l-8.92-8.92c-.36-.36-.94-.36-1.31,0s-.36.94,0,1.31l8.92,8.92h-12.62c-.51,0-.92.41-.92.92s.41.92.92.92h12.62l-8.92,8.92c-.36.36-.36.94,0,1.31.18.18.42.27.65.27s.47-.09.65-.27l8.92-8.92v12.62c0,.51.41.92.92.92s.92-.41.92-.92v-12.62l8.92,8.92c.18.18.42.27.65.27s.47-.09.65-.27c.36-.36.36-.94,0-1.31l-8.92-8.92h12.62c.51,0,.92-.41.92-.92s-.41-.92-.92-.92Z\"/>\n    <path class=\"cls-9\" d=\"M36.85,80.19h-12.62l8.92-8.92c.36-.36.36-.94,0-1.31-.36-.36-.94-.36-1.31,0l-8.92,8.92v-12.62c0-.51-.41-.92-.92-.92s-.92.41-.92.92v12.62l-8.92-8.92c-.36-.36-.94-.36-1.31,0-.36.36-.36.94,0,1.31l8.92,8.92H7.16c-.51,0-.92.41-.92.92s.41.92.92.92h12.62l-8.92,8.92c-.36.36-.36.94,0,1.31.18.18.42.27.65.27s.47-.09.65-.27l8.92-8.92v12.62c0,.51.41.92.92.92s.92-.41.92-.92v-12.62l8.92,8.92c.18.18.42.27.65.27s.47-.09.65-.27c.36-.36.36-.94,0-1.31l-8.92-8.92h12.62c.51,0,.92-.41.92-.92s-.41-.92-.92-.92Z\"/>\n    <path class=\"cls-9\" d=\"M97.8,134.09h-12.62l8.92-8.92c.36-.36.36-.94,0-1.31s-.94-.36-1.31,0l-8.92,8.92v-12.62c0-.51-.41-.92-.92-.92s-.92.41-.92.92v12.62l-8.92-8.92c-.36-.36-.94-.36-1.31,0s-.36.94,0,1.31l8.92,8.92h-12.62c-.51,0-.92.41-.92.92s.41.92.92.92h12.62l-8.92,8.92c-.36.36-.36.94,0,1.31.18.18.42.27.65.27s.47-.09.65-.27l8.92-8.92v12.62c0,.51.41.92.92.92s.92-.41.92-.92v-12.62l8.92,8.92c.18.18.42.27.65.27s.47-.09.65-.27c.36-.36.36-.94,0-1.31l-8.92-8.92h12.62c.51,0,.92-.41.92-.92s-.41-.92-.92-.92Z\"/>\n    <path class=\"cls-5\" d=\"M54.72,118.32h-12.62l8.92-8.92c.36-.36.36-.94,0-1.31s-.94-.36-1.31,0l-8.92,8.92v-12.62c0-.51-.41-.92-.92-.92s-.92.41-.92.92v12.62l-8.92-8.92c-.36-.36-.94-.36-1.31,0s-.36.94,0,1.31l8.92,8.92h-12.62c-.51,0-.92.41-.92.92s.41.92.92.92h12.62l-8.92,8.92c-.36.36-.36.94,0,1.31.18.18.42.27.65.27s.47-.09.65-.27l8.92-8.92v12.62c0,.51.41.92.92.92s.92-.41.92-.92v-12.62l8.92,8.92c.18.18.42.27.65.27s.47-.09.65-.27c.36-.36.36-.94,0-1.31l-8.92-8.92h12.62c.51,0,.92-.41.92-.92s-.41-.92-.92-.92Z\"/>\n    <path class=\"cls-5\" d=\"M142.04,122.36h-12.62l8.92-8.92c.36-.36.36-.94,0-1.31s-.94-.36-1.31,0l-8.92,8.92v-12.62c0-.51-.41-.92-.92-.92s-.92.41-.92.92v12.62l-8.92-8.92c-.36-.36-.94-.36-1.31,0s-.36.94,0,1.31l8.92,8.92h-12.62c-.51,0-.92.41-.92.92s.41.92.92.92h12.62l-8.92,8.92c-.36.36-.36.94,0,1.31.18.18.42.27.65.27s.47-.09.65-.27l8.92-8.92v12.62c0,.51.41.92.92.92s.92-.41.92-.92v-12.62l8.92,8.92c.18.18.42.27.65.27s.47-.09.65-.27c.36-.36.36-.94,0-1.31l-8.92-8.92h12.62c.51,0,.92-.41.92-.92s-.41-.92-.92-.92Z\"/>\n    <circle class=\"cls-5\" cx=\"62.53\" cy=\"57.53\" r=\"4.27\"/>\n    <circle class=\"cls-5\" cx=\"110.43\" cy=\"15.72\" r=\"4.19\"/>\n    <circle class=\"cls-5\" cx=\"99.01\" cy=\"108.66\" r=\"4.16\"/>\n    <circle class=\"cls-9\" cx=\"106.21\" cy=\"147.27\" r=\"4.71\"/>\n    <circle class=\"cls-5\" cx=\"150.11\" cy=\"104.5\" r=\"4.25\"/>\n    <circle class=\"cls-6\" cx=\"150.11\" cy=\"52.39\" r=\"4.71\"/>\n    <circle class=\"cls-9\" cx=\"58.25\" cy=\"13.24\" r=\"4.71\"/>\n    <circle class=\"cls-5\" cx=\"17.69\" cy=\"54.09\" r=\"4.32\"/>\n    <circle class=\"cls-9\" cx=\"56.6\" cy=\"91.54\" r=\"4.71\"/>\n    <circle class=\"cls-5\" cx=\"54.08\" cy=\"144.92\" r=\"4.17\"/>\n    <circle class=\"cls-5\" cx=\"94\" cy=\"24.58\" r=\"2.82\"/>\n    <circle class=\"cls-5\" cx=\"101.65\" cy=\"49.47\" r=\"1.51\"/>\n    <circle class=\"cls-5\" cx=\"132.96\" cy=\"28.16\" r=\"1.51\"/>\n    <line class=\"cls-2\" x1=\"123.57\" y1=\"24.29\" x2=\"123.57\" y2=\"60.38\"/>\n    <line class=\"cls-2\" x1=\"123.57\" y1=\"38.48\" x2=\"126.94\" y2=\"35.01\"/>\n    <line class=\"cls-2\" x1=\"120.21\" y1=\"35.01\" x2=\"123.57\" y2=\"38.48\"/>\n    <line class=\"cls-2\" x1=\"123.57\" y1=\"34.17\" x2=\"126.94\" y2=\"30.7\"/>\n    <line class=\"cls-2\" x1=\"120.21\" y1=\"30.7\" x2=\"123.57\" y2=\"34.17\"/>\n    <line class=\"cls-2\" x1=\"123.57\" y1=\"29.86\" x2=\"126.94\" y2=\"26.39\"/>\n    <line class=\"cls-2\" x1=\"120.21\" y1=\"26.39\" x2=\"123.57\" y2=\"29.86\"/>\n    <line class=\"cls-2\" x1=\"123.57\" y1=\"46.19\" x2=\"120.21\" y2=\"49.66\"/>\n    <line class=\"cls-2\" x1=\"126.94\" y1=\"49.66\" x2=\"123.57\" y2=\"46.19\"/>\n    <line class=\"cls-2\" x1=\"123.57\" y1=\"50.5\" x2=\"120.21\" y2=\"53.97\"/>\n    <line class=\"cls-2\" x1=\"126.94\" y1=\"53.97\" x2=\"123.57\" y2=\"50.5\"/>\n    <line class=\"cls-2\" x1=\"123.57\" y1=\"54.8\" x2=\"120.21\" y2=\"58.28\"/>\n    <line class=\"cls-2\" x1=\"126.94\" y1=\"58.28\" x2=\"123.57\" y2=\"54.8\"/>\n    <line class=\"cls-2\" x1=\"107.94\" y1=\"33.31\" x2=\"139.2\" y2=\"51.36\"/>\n    <line class=\"cls-2\" x1=\"120.23\" y1=\"40.41\" x2=\"118.91\" y2=\"35.76\"/>\n    <line class=\"cls-2\" x1=\"115.54\" y1=\"41.59\" x2=\"120.23\" y2=\"40.41\"/>\n    <line class=\"cls-2\" x1=\"116.5\" y1=\"38.25\" x2=\"115.18\" y2=\"33.6\"/>\n    <line class=\"cls-2\" x1=\"111.81\" y1=\"39.43\" x2=\"116.5\" y2=\"38.25\"/>\n    <line class=\"cls-2\" x1=\"112.77\" y1=\"36.1\" x2=\"111.45\" y2=\"31.45\"/>\n    <line class=\"cls-2\" x1=\"108.08\" y1=\"37.28\" x2=\"112.77\" y2=\"36.1\"/>\n    <line class=\"cls-2\" x1=\"126.91\" y1=\"44.26\" x2=\"128.23\" y2=\"48.91\"/>\n    <line class=\"cls-2\" x1=\"131.6\" y1=\"43.08\" x2=\"126.91\" y2=\"44.26\"/>\n    <line class=\"cls-2\" x1=\"130.64\" y1=\"46.42\" x2=\"131.96\" y2=\"51.07\"/>\n    <line class=\"cls-2\" x1=\"135.33\" y1=\"45.24\" x2=\"130.64\" y2=\"46.41\"/>\n    <line class=\"cls-2\" x1=\"134.37\" y1=\"48.57\" x2=\"135.69\" y2=\"53.22\"/>\n    <line class=\"cls-2\" x1=\"139.06\" y1=\"47.39\" x2=\"134.37\" y2=\"48.57\"/>\n    <line class=\"cls-2\" x1=\"139.2\" y1=\"33.31\" x2=\"107.94\" y2=\"51.36\"/>\n    <line class=\"cls-2\" x1=\"126.91\" y1=\"40.41\" x2=\"131.6\" y2=\"41.59\"/>\n    <line class=\"cls-2\" x1=\"128.23\" y1=\"35.76\" x2=\"126.91\" y2=\"40.41\"/>\n    <line class=\"cls-2\" x1=\"130.64\" y1=\"38.25\" x2=\"135.33\" y2=\"39.43\"/>\n    <line class=\"cls-2\" x1=\"131.96\" y1=\"33.6\" x2=\"130.64\" y2=\"38.25\"/>\n    <line class=\"cls-2\" x1=\"134.37\" y1=\"36.1\" x2=\"139.06\" y2=\"37.28\"/>\n    <line class=\"cls-2\" x1=\"135.69\" y1=\"31.45\" x2=\"134.37\" y2=\"36.1\"/>\n    <line class=\"cls-2\" x1=\"120.23\" y1=\"44.26\" x2=\"115.54\" y2=\"43.08\"/>\n    <line class=\"cls-2\" x1=\"118.91\" y1=\"48.91\" x2=\"120.23\" y2=\"44.26\"/>\n    <line class=\"cls-2\" x1=\"116.5\" y1=\"46.41\" x2=\"111.81\" y2=\"45.24\"/>\n    <line class=\"cls-2\" x1=\"115.18\" y1=\"51.07\" x2=\"116.5\" y2=\"46.42\"/>\n    <line class=\"cls-2\" x1=\"112.77\" y1=\"48.57\" x2=\"108.08\" y2=\"47.39\"/>\n    <line class=\"cls-2\" x1=\"111.45\" y1=\"53.22\" x2=\"112.77\" y2=\"48.57\"/>\n    <path class=\"cls-6\" d=\"M145.84,67.5h-6.28l4.44-4.44c.18-.18.18-.47,0-.65-.18-.18-.47-.18-.65,0l-4.44,4.44v-6.28c0-.25-.21-.46-.46-.46s-.46.21-.46.46v6.28l-4.44-4.44c-.18-.18-.47-.18-.65,0-.18.18-.18.47,0,.65l4.44,4.44h-6.28c-.25,0-.46.21-.46.46s.21.46.46.46h6.28l-4.44,4.44c-.18.18-.18.47,0,.65.09.09.21.13.33.13s.24-.04.33-.13l4.44-4.44v6.28c0,.25.21.46.46.46s.46-.21.46-.46v-6.28l4.44,4.44c.09.09.21.13.33.13s.24-.04.33-.13c.18-.18.18-.47,0-.65l-4.44-4.44h6.28c.25,0,.46-.21.46-.46s-.21-.46-.46-.46Z\"/>\n    <path class=\"cls-6\" d=\"M98.28,11.38h-2.45l1.73-1.73c.07-.07.07-.18,0-.25-.07-.07-.18-.07-.25,0l-1.73,1.73v-2.45c0-.1-.08-.18-.18-.18s-.18.08-.18.18v2.45l-1.73-1.73c-.07-.07-.18-.07-.25,0-.07.07-.07.18,0,.25l1.73,1.73h-2.45c-.1,0-.18.08-.18.18s.08.18.18.18h2.45l-1.73,1.73c-.07.07-.07.18,0,.25.03.03.08.05.13.05s.09-.02.13-.05l1.73-1.73v2.45c0,.1.08.18.18.18s.18-.08.18-.18v-2.45l1.73,1.73s.08.05.13.05.09-.02.13-.05c.07-.07.07-.18,0-.25l-1.73-1.73h2.45c.1,0,.18-.08.18-.18s-.08-.18-.18-.18Z\"/>\n    <path class=\"cls-6\" d=\"M124.59,73.09c.03.17-.41,1.49-.49,1.75.27.48.62,1,.92,1.47-.52-.15-1.14-.33-1.67-.46-.29.17-1.45,1.01-1.64,1.06.15-.56.46-1.30.58-1.85-.33-.49-.64-.98-.94-1.49.56.17,1.13.32,1.69.48.51-.30,1.02-.66,1.54-.96Z\"/>\n    <path class=\"cls-6\" d=\"M107.28,27.78c-.1.14-1.32.8-1.56.93-.13.54-.24,1.15-.34,1.7-.27-.47-.60-1.03-.89-1.48-.33-.07-1.75-.27-1.92-.36.49-.30,1.23-.62,1.69-.94.10-.58.22-1.15.35-1.73.29.51.59,1.01.90,1.51.58.14,1.20.22,1.78.37Z\"/>\n    <polyline class=\"cls-3\" points=\"105.9 66.61 105.31 66.71 103.22 67.08\"/>\n    <polyline class=\"cls-3\" points=\"109.81 65.93 110.4 65.83 112.49 65.47\"/>\n    <line class=\"cls-3\" x1=\"110.4\" y1=\"65.83\" x2=\"112.18\" y2=\"66.86\"/>\n    <line class=\"cls-3\" x1=\"110.4\" y1=\"65.83\" x2=\"111.73\" y2=\"64.26\"/>\n    <line class=\"cls-3\" x1=\"105.31\" y1=\"66.71\" x2=\"103.53\" y2=\"65.68\"/>\n    <line class=\"cls-3\" x1=\"105.31\" y1=\"66.71\" x2=\"103.98\" y2=\"68.29\"/>\n    <polyline class=\"cls-3\" points=\"106.23 65.13 105.75 64.79 104.01 63.57\"/>\n    <polyline class=\"cls-3\" points=\"109.48 67.42 109.96 67.76 111.7 68.98\"/>\n    <line class=\"cls-3\" x1=\"109.96\" y1=\"67.76\" x2=\"110.5\" y2=\"69.75\"/>\n    <line class=\"cls-3\" x1=\"109.96\" y1=\"67.76\" x2=\"112.02\" y2=\"67.58\"/>\n    <line class=\"cls-3\" x1=\"105.75\" y1=\"64.79\" x2=\"105.21\" y2=\"62.79\"/>\n    <line class=\"cls-3\" x1=\"105.75\" y1=\"64.79\" x2=\"103.69\" y2=\"64.96\"/>\n    <polyline class=\"cls-3\" points=\"106.71 67.9 106.71 67.9 106.37 68.38 106.37 68.38 105.15 70.12\"/>\n    <polyline class=\"cls-3\" points=\"109 64.65 109 64.64 109.34 64.16 109.34 64.16 110.56 62.43\"/>\n    <line class=\"cls-3\" x1=\"109.34\" y1=\"64.16\" x2=\"109.17\" y2=\"62.11\"/>\n    <line class=\"cls-3\" x1=\"109.34\" y1=\"64.16\" x2=\"111.33\" y2=\"63.63\"/>\n    <line class=\"cls-3\" x1=\"106.37\" y1=\"68.38\" x2=\"106.54\" y2=\"70.44\"/>\n    <line class=\"cls-3\" x1=\"106.37\" y1=\"68.38\" x2=\"104.38\" y2=\"68.91\"/>\n    <polyline class=\"cls-3\" points=\"107.51 64.31 107.41 63.73 107.05 61.64\"/>\n    <polyline class=\"cls-3\" points=\"108.2 68.23 108.3 68.81 108.66 70.90\"/>\n    <line class=\"cls-3\" x1=\"108.3\" y1=\"68.81\" x2=\"107.27\" y2=\"70.6\"/>\n    <line class=\"cls-3\" x1=\"108.3\" y1=\"68.81\" x2=\"109.87\" y2=\"70.14\"/>\n    <line class=\"cls-3\" x1=\"107.41\" y1=\"63.73\" x2=\"108.44\" y2=\"61.94\"/>\n    <line class=\"cls-3\" x1=\"107.41\" y1=\"63.73\" x2=\"105.84\" y2=\"62.4\"/>\n    <polygon class=\"cls-3\" points=\"109.81 65.93 108.83 66.49 109.48 67.42 108.39 67.11 108.2 68.23 107.64 67.24 106.71 67.9 107.02 66.8 105.9 66.61 106.88 66.05 106.23 65.13 107.32 65.43 107.51 64.31 108.07 65.3 109 64.64 108.69 65.74 109.81 65.93\"/>\n    <circle class=\"cls-5\" cx=\"123.3\" cy=\"64.85\" r=\"1.97\"/>\n    <circle class=\"cls-5\" cx=\"155.74\" cy=\"72.41\" r=\"1.41\"/>\n    <circle class=\"cls-5\" cx=\"86.8\" cy=\"19.05\" r=\"1.13\"/>\n    <circle class=\"cls-5\" cx=\"101.96\" cy=\"77.22\" r=\"1.13\"/>\n  </g>\n</svg>`;\n      \n      const img = new Image();\n      const svg = new Blob([svgString], { type: 'image/svg+xml' });\n      const url = URL.createObjectURL(svg);\n      \n      img.onload = function() {\n        context.drawImage(img, x, y, size, size);\n        URL.revokeObjectURL(url);\n      };\n      \n      img.src = url;\n    }\n\n    function downloadCanvasAsImage() {\n      let image = canvas.toDataURL('image/png').replace('image/png', 'image/octet-stream');\n      let link = document.createElement('a');\n      link.download = 'my-canvas.png';\n      link.href = image;\n      link.click();\n    }\n\n    function randomPalette() {\n      const randomIndex = Math.floor(Math.random() * (colorPalettes.length - 1)) + 1;\n      colors = colorPalettes[randomIndex];\n      isChristmasMode = false;\n      drawGrid();\n    }\n\n    function christmasMode() {\n      colors = colorPalettes[0]; // AZ Blue palette\n      isChristmasMode = true;\n      selectedSvgDesign = 3; // Always use design 3 (snowflakes with varied sizes)\n      // Commented out random selection - uncomment to enable multiple SVG designs:\n      // selectedSvgDesign = Math.floor(Math.random() * 4);\n      drawGrid();\n    }\n\n    window.addEventListener('resize', () => {\n      setCanvasSize();\n      drawGrid();\n    });\n\n    document.getElementById('downloadBtn').addEventListener('click', downloadCanvasAsImage);\n\n    function refreshPage() {\n      colors = colorPalettes[0]; // AZ Blue palette\n      isChristmasMode = false;\n      drawGrid();\n    }\n\n    setCanvasSize();\n    drawGrid();\n  </script>\n</body>\n</html>",
    "demo": "",
    "date": "2026-01-01T08:19:14.821Z"
  }
]