{
  "version": "2.3.5",
  "updatedAt": "2026-06-04T00:00:00.000Z",
  "downloadUrl": "https://www.tylervinson.com/widget/",
  "widgets": [
    {
      "class": "animated-cards",
      "name": "Animated Cards",
      "repeat": {
        "selector": ".profile-card",
        "groupLabel": "Card"
      },
      "fields": [
        {
          "key": "number",
          "label": "Statistic Value",
          "selector": ".number",
          "type": "text",
          "syncDataAttr": "data-target",
          "syncNumeric": true
        },
        {
          "key": "text",
          "label": "Card Label",
          "selector": ".copy-text",
          "type": "text"
        }
      ]
    },
    {
      "class": "insurance-comparison-tool",
      "name": "Insurance Plan Comparison Tool",
      "standaloneFields": [
        {
          "key": "heading",
          "label": "Section Heading",
          "selector": "h1",
          "type": "text"
        }
      ],
      "repeat": {
        "selector": ".plan-button",
        "groupLabel": "Plan",
        "groupLabelField": "name"
      },
      "fields": [
        {
          "key": "type",
          "label": "Plan Type",
          "selector": ".plan-button-type",
          "type": "text"
        },
        {
          "key": "name",
          "label": "Plan Name",
          "selector": ".plan-button-name",
          "type": "text"
        },
        {
          "key": "coverage",
          "label": "Coverage Type",
          "selector": ".plan-button-coverage",
          "type": "text"
        },
        {
          "key": "price",
          "label": "Monthly Price",
          "gridSelector": ".comparison-grid",
          "gridCellSelector": "[data-comparison='price'] [data-plan='{planNum}']"
        },
        {
          "key": "deductible",
          "label": "Annual Deductible",
          "gridSelector": ".comparison-grid",
          "gridCellSelector": "[data-comparison='deductible'] [data-plan='{planNum}']"
        },
        {
          "key": "maxOutOfPocket",
          "label": "Max Out-of-Pocket",
          "gridSelector": ".comparison-grid",
          "gridCellSelector": "[data-comparison='maxOutOfPocket'] [data-plan='{planNum}']"
        },
        {
          "key": "coveragePercent",
          "label": "Coverage Percentage",
          "gridSelector": ".comparison-grid",
          "gridCellSelector": "[data-comparison='coveragePercent'] [data-plan='{planNum}']"
        },
        {
          "key": "doctorVisits",
          "label": "Doctor Visit Copay",
          "gridSelector": ".comparison-grid",
          "gridCellSelector": "[data-comparison='doctorVisits'] [data-plan='{planNum}']"
        },
        {
          "key": "prescription",
          "label": "Prescription Coverage",
          "gridSelector": ".comparison-grid",
          "gridCellSelector": "[data-comparison='prescription'] [data-plan='{planNum}']"
        },
        {
          "key": "emergency",
          "label": "Emergency Care Copay",
          "gridSelector": ".comparison-grid",
          "gridCellSelector": "[data-comparison='emergency'] [data-plan='{planNum}']"
        },
        {
          "key": "mentalHealth",
          "label": "Mental Health Coverage",
          "gridSelector": ".comparison-grid",
          "gridCellSelector": "[data-comparison='mentalHealth'] [data-plan='{planNum}']"
        },
        {
          "key": "dentalVision",
          "label": "Dental & Vision",
          "gridSelector": ".comparison-grid",
          "gridCellSelector": "[data-comparison='dentalVision'] [data-plan='{planNum}']"
        }
      ]
    },
    {
      "class": "zoom-meetings",
      "name": "Zoom Meetings",
      "repeat": {
        "selector": ".zmw-meeting",
        "groupLabel": "Meeting",
        "groupLabelField": "title",
        "dateField": "datetime",
        "dateAttr": "data-end",
        "newItemTemplate": "<div class=\"zmw-meeting\" data-register-url=\"\" data-end=\"{date}\"><div class=\"zmw-date-block\"><div class=\"zmw-month\">{month}</div><div class=\"zmw-day\">{day}</div><div class=\"zmw-time\">{time}</div></div><div class=\"zmw-content\"><div class=\"zmw-title\"><span class=\"zmw-title-text\">{title}</span><div class=\"zmw-register-wrap\" hidden><a class=\"zmw-register-btn appearance-none duration-200 ease-in-out align-middle inline-flex items-center justify-center leading-none rounded-full text-sm transition-colors whitespace-pre-line sm:whitespace-pre bg-btn-bg-secondary font-bolder hover:bg-btn-bg-secondary-hover hover:ring-2 hover:ring-btn-border-secondary-hover hover:text-btn-text-secondary-hover ring-1 ring-btn-border-secondary text-btn-text-secondary text-base sm:w-auto w-full px-8 py-2\" target=\"_blank\" rel=\"noopener noreferrer\">Register Here</a></div><svg class=\"zmw-chevron\" viewBox=\"0 0 20 20\" aria-hidden=\"true\"><path d=\"M4 7l6 6 6-6\" stroke-linecap=\"round\" stroke-linejoin=\"round\"/></svg></div><div class=\"zmw-description\">{description}</div><div class=\"zmw-extender\"><p>{details}</p></div></div></div>"
      },
      "fields": [
        {
          "key": "datetime",
          "label": "Date & Time",
          "selector": null,
          "attr": "data-end",
          "type": "datetime-local",
          "hint": "Sets the date, time, and expiry automatically"
        },
        {
          "key": "title",
          "label": "Meeting Title",
          "selector": ".zmw-title-text",
          "type": "text"
        },
        {
          "key": "description",
          "label": "Short Description",
          "selector": ".zmw-description",
          "type": "text"
        },
        {
          "key": "registerUrl",
          "label": "Registration URL",
          "type": "url",
          "attr": "data-register-url",
          "hint": "Full external URL (https://...). Leave blank to hide the Register button."
        },
        {
          "key": "details",
          "label": "Detail Body",
          "selector": ".zmw-extender",
          "type": "richtext"
        }
      ]
    }
  ],
  "apiKey": "{90524103-7799-489C-9E53-C0D995207FB4}"
}